{
  "type": "Feature",
  "properties": {
    "gn:admin1_code":"17",
    "gn:asciiname":"Dar Cheikh Ali",
    "gn:cc2":"TN",
    "gn:country_code":"TN",
    "gn:dem":213,
    "gn:feature_class":"P",
    "gn:feature_code":"PPL",
    "gn:name":"Dar Che\u00efkh Ali",
    "gn:population":0,
    "gn:timezone":"Africa/Tunis",
    "iso:country":"TN",
    "name:und_x_variant":[
        "Dar Che\u00efkr Ali",
        "Dar Che\u00efkh Ali"
    ],
    "wof:name":"Dar Cheikh Ali",
    "wof:placetype":"locality"
},
  "geometry": {"coordinates":[9.78111,36.3325],"type":"Point"}
}