{
  "type": "Feature",
  "properties": {
    "gn:admin1_code":"29",
    "gn:asciiname":"Nahal",
    "gn:country_code":"TN",
    "gn:dem":23,
    "gn:feature_class":"P",
    "gn:feature_code":"PPL",
    "gn:name":"Nahal",
    "gn:population":0,
    "gn:timezone":"Africa/Tunis",
    "iso:country":"TN",
    "name:deu_x_preferred":[
        "Nachal"
    ],
    "name:fra_x_preferred":[
        "Nahal"
    ],
    "name:por_x_preferred":[
        "Nahal"
    ],
    "name:und_x_variant":[
        "An Na\u1e29l"
    ],
    "wof:lang_x_official":[
        "ara",
        "fra"
    ],
    "wof:lang_x_spoken":[
        "ara",
        "fra"
    ],
    "wof:name":"Nahal",
    "wof:placetype":"locality"
},
  "geometry": {"coordinates":[10.07295,33.8882],"type":"Point"}
}