{
  "type": "Feature",
  "properties": {
    "iso:country":"TN",
    "name:ara_x_preferred":[
        "El Halfaouine"
    ],
    "qs:gn_adm0_cc":"TN",
    "qs:gn_local":2464470,
    "qs:gn_nam_loc":"\u062a\u0648\u0646\u0633, Tunis, TN",
    "qs:gn_namadm1":"36",
    "qs:local_max":1018,
    "qs:local_sum":7193,
    "qs:localhoods":20,
    "qs:name":"El Halfaouine",
    "qs:name_adm0":"Tunisia",
    "qs:name_adm1":"Tunis",
    "qs:name_local":"\u062a\u0648\u0646\u0633",
    "qs:photo_max":86,
    "qs:photo_sum":358,
    "qs:placetype":"Suburb",
    "qs:quad_count":15,
    "qs:woe_adm0":23424967,
    "qs:woe_adm1":2347256,
    "qs:woe_adm2":0,
    "qs:woe_lau":0,
    "qs:woe_local":1442746,
    "qs:woe_ver":"7.10.0",
    "wof:name":"El Halfaouine",
    "wof:placetype":"neighbourhood"
},
  "geometry": {"coordinates":[10.169838,36.804376],"type":"Point"}
}