{
  "type": "Feature",
  "properties": {
    "gn:admin1_code":"36",
    "gn:asciiname":"El mourouj 2",
    "gn:country_code":"TN",
    "gn:dem":41,
    "gn:feature_class":"P",
    "gn:feature_code":"PPL",
    "gn:name":"El mourouj 2",
    "gn:population":0,
    "gn:timezone":"Africa/Tunis",
    "iso:country":"TN",
    "wof:name":"El mourouj 2",
    "wof:placetype":"locality"
},
  "geometry": {"coordinates":[10.2002,36.74232],"type":"Point"}
}