{
  "type": "Feature",
  "properties": {
    "gn:admin1_code":"29",
    "gn:asciiname":"Rhennouch",
    "gn:country_code":"TN",
    "gn:dem":18,
    "gn:feature_class":"P",
    "gn:feature_code":"PPL",
    "gn:name":"Rhennouch",
    "gn:population":0,
    "gn:timezone":"Africa/Tunis",
    "iso:country":"TN",
    "name:ara_x_preferred":[
        "\u063a\u0646\u0648\u0634"
    ],
    "name:cat_x_preferred":[
        "Ghannouch"
    ],
    "name:deu_x_preferred":[
        "Ghannouch"
    ],
    "name:fra_x_preferred":[
        "Ghannouch"
    ],
    "name:ukr_x_preferred":[
        "\u0413\u0430\u043d\u0443\u0448"
    ],
    "name:und_x_variant":[
        "Rhennoucha",
        "Grenush",
        "Rhennouch",
        "Ghann\u016bsh"
    ],
    "wof:name":"Rhennouch",
    "wof:placetype":"locality"
},
  "geometry": {"coordinates":[10.06439,33.94055],"type":"Point"}
}