{
  "type": "Feature",
  "properties": {
    "gn:admin1_code":"29",
    "gn:asciiname":"Toudjane",
    "gn:country_code":"TN",
    "gn:dem":468,
    "gn:feature_class":"P",
    "gn:feature_code":"PPL",
    "gn:name":"Toudjane",
    "gn:population":0,
    "gn:timezone":"Africa/Tunis",
    "iso:country":"TN",
    "name:ara_x_preferred":[
        "\u062a\u0648\u062c\u0627\u0646"
    ],
    "name:cat_x_preferred":[
        "Toujane"
    ],
    "name:fra_x_preferred":[
        "Toujane"
    ],
    "name:por_x_preferred":[
        "Toujane"
    ],
    "name:spa_x_preferred":[
        "Toujane"
    ],
    "name:und_x_variant":[
        "Toudjane",
        "T\u016bj\u0101n"
    ],
    "wof:name":"Toudjane",
    "wof:placetype":"locality"
},
  "geometry": {"coordinates":[10.13375,33.46518],"type":"Point"}
}