{
  "type": "Feature",
  "properties": {
    "gn:gn_country":"TN",
    "gn:gn_fcode":"PPL",
    "gn:gn_pop":6969,
    "gn:population":6969,
    "iso:country":"TN",
    "name:ara_x_preferred":[
        "\u0627\u0644\u0645\u0639\u0645\u0648\u0631\u0629"
    ],
    "name:dut_x_preferred":[
        "El Ma\u00e2moura"
    ],
    "name:eng_x_preferred":[
        "El Ma\u00e2moura"
    ],
    "name:fre_x_preferred":[
        "El Ma\u00e2moura"
    ],
    "name:ukr_x_preferred":[
        "\u0415\u043b\u044c-\u041c\u0430\u0430\u043c\u0443\u0440\u0430"
    ],
    "name:unk_x_variant":[
        "Al Ma\u2018m\u016brah"
    ],
    "qs_pg:aaroncc":"TN",
    "qs_pg:gn_country":"TN",
    "qs_pg:gn_fcode":"PPL",
    "qs_pg:gn_pop":6969,
    "qs_pg:name":"El Maamoura",
    "qs_pg:photos_9r":0,
    "qs_pg:photos_sr":0,
    "qs_pg:pop_sr":5,
    "qs_pg:qs_pg_placetype":"locality",
    "wof:name":"El Maamoura",
    "wof:placetype":"locality",
    "wof:population":6969
},
  "geometry": {"coordinates":[10.80612,36.46499],"type":"Point"}
}