{
  "type": "Feature",
  "properties": {
    "gn:admin1_code":"36",
    "gn:asciiname":"Fochville",
    "gn:country_code":"TN",
    "gn:dem":5,
    "gn:feature_class":"P",
    "gn:feature_code":"PPL",
    "gn:name":"Fochville",
    "gn:population":0,
    "gn:timezone":"Africa/Tunis",
    "iso:country":"TN",
    "name:afr_x_preferred":[
        "Fochville"
    ],
    "name:ceb_x_preferred":[
        "Fochville"
    ],
    "name:est_x_preferred":[
        "Fochville"
    ],
    "name:fra_x_preferred":[
        "Fochville"
    ],
    "name:mlg_x_preferred":[
        "Fochville"
    ],
    "name:nld_x_preferred":[
        "Fochville"
    ],
    "name:nso_x_preferred":[
        "Fochville"
    ],
    "name:pol_x_preferred":[
        "Fochville"
    ],
    "name:ron_x_preferred":[
        "Fochville"
    ],
    "name:rus_x_preferred":[
        "\u0424\u043e\u0448\u0432\u0438\u043b\u043b"
    ],
    "wof:name":"Fochville",
    "wof:placetype":"locality"
},
  "geometry": {"coordinates":[10.22389,36.75833],"type":"Point"}
}