{
  "type": "Feature",
  "properties": {
    "gn:admin1_code":"02",
    "gn:asciiname":"Douar Oulad Messaoud",
    "gn:country_code":"TN",
    "gn:dem":740,
    "gn:feature_class":"P",
    "gn:feature_code":"PPL",
    "gn:name":"Douar Oulad Messaoud",
    "gn:population":0,
    "gn:timezone":"Africa/Tunis",
    "iso:country":"TN",
    "name:und_x_variant":[
        "Daww\u0101r Awl\u0101d Mas\u2018\u016bd"
    ],
    "wof:name":"Douar Oulad Messaoud",
    "wof:placetype":"locality"
},
  "geometry": {"coordinates":[8.73114,35.73827],"type":"Point"}
}