{
  "type": "Feature",
  "properties": {
    "gn:admin1_code":"28",
    "gn:asciiname":"Ksar el Djouama",
    "gn:country_code":"TN",
    "gn:dem":439,
    "gn:feature_class":"P",
    "gn:feature_code":"PPL",
    "gn:name":"Ksar el Djouama",
    "gn:population":0,
    "gn:timezone":"Africa/Tunis",
    "iso:country":"TN",
    "name:und_x_variant":[
        "Ksar el Djouamea",
        "Ksar el Djouama",
        "Qa\u015fr al Jaw\u0101mi\u2018"
    ],
    "wof:lang_x_official":[
        "ara",
        "fra"
    ],
    "wof:lang_x_spoken":[
        "ara",
        "fra"
    ],
    "wof:name":"Ksar el Djouama",
    "wof:placetype":"locality"
},
  "geometry": {"coordinates":[10.25879,33.23524],"type":"Point"}
}