{
  "type": "Feature",
  "properties": {
    "gn:admin1_code":"28",
    "gn:asciiname":"El Hazem",
    "gn:country_code":"TN",
    "gn:dem":25,
    "gn:feature_class":"P",
    "gn:feature_code":"PPL",
    "gn:name":"El Hazem",
    "gn:population":0,
    "gn:timezone":"Africa/Tunis",
    "iso:country":"TN",
    "name:und_x_variant":[
        "Al \u1e28\u0101zim"
    ],
    "wof:name":"El Hazem",
    "wof:placetype":"locality"
},
  "geometry": {"coordinates":[10.93333,33.78333],"type":"Point"}
}