{
  "type": "Feature",
  "properties": {
    "gn:admin1_code":"15",
    "gn:asciiname":"Houmet el Jerbou",
    "gn:country_code":"TN",
    "gn:dem":1,
    "gn:feature_class":"P",
    "gn:feature_code":"PPL",
    "gn:name":"Houmet el Jerbou",
    "gn:population":0,
    "gn:timezone":"Africa/Tunis",
    "iso:country":"TN",
    "wof:name":"Houmet el Jerbou",
    "wof:placetype":"locality"
},
  "geometry": {"coordinates":[11.04528,35.51944],"type":"Point"}
}