{
  "type": "Feature",
  "properties": {
    "gn:admin1_code":"19",
    "gn:asciiname":"Dar el Kharaz",
    "gn:country_code":"TN",
    "gn:dem":102,
    "gn:feature_class":"P",
    "gn:feature_code":"PPL",
    "gn:name":"Dar el Kharaz",
    "gn:population":0,
    "gn:timezone":"Africa/Tunis",
    "iso:country":"TN",
    "wof:name":"Dar el Kharaz",
    "wof:placetype":"locality"
},
  "geometry": {"coordinates":[10.75976,36.67889],"type":"Point"}
}