{
  "type": "Feature",
  "properties": {
    "gn:admin1_code":"27",
    "gn:asciiname":"Douar el Haj Ahmed",
    "gn:cc2":"TN",
    "gn:country_code":"TN",
    "gn:dem":79,
    "gn:feature_class":"P",
    "gn:feature_code":"PPL",
    "gn:name":"Douar el Haj Ahmed",
    "gn:population":0,
    "gn:timezone":"Africa/Tunis",
    "iso:country":"TN",
    "name:und_x_variant":[
        "Douar el Hadj Ahmed",
        "Douar el Haj Ahmed"
    ],
    "wof:name":"Douar el Haj Ahmed",
    "wof:placetype":"locality"
},
  "geometry": {"coordinates":[10.27889,36.60222],"type":"Point"}
}