{
  "type": "Feature",
  "properties": {
    "gn:admin1_code":"19",
    "gn:asciiname":"Dar Ben Slimane",
    "gn:country_code":"TN",
    "gn:dem":13,
    "gn:feature_class":"P",
    "gn:feature_code":"PPL",
    "gn:name":"Dar Ben Slimane",
    "gn:population":0,
    "gn:timezone":"Africa/Tunis",
    "iso:country":"TN",
    "wof:name":"Dar Ben Slimane",
    "wof:placetype":"locality"
},
  "geometry": {"coordinates":[10.87667,36.61778],"type":"Point"}
}