{
  "type": "Feature",
  "properties": {
    "gn:admin1_code":"38",
    "gn:asciiname":"Jaafar",
    "gn:country_code":"TN",
    "gn:dem":89,
    "gn:feature_class":"P",
    "gn:feature_code":"PPL",
    "gn:name":"Jaafar",
    "gn:population":0,
    "gn:timezone":"Africa/Tunis",
    "iso:country":"TN",
    "wof:name":"Jaafar",
    "wof:placetype":"locality"
},
  "geometry": {"coordinates":[10.14333,36.91444],"type":"Point"}
}