{
  "type": "Feature",
  "properties": {
    "gn:admin1_code":"23",
    "gn:asciiname":"Oulad Messaouda",
    "gn:country_code":"TN",
    "gn:dem":22,
    "gn:feature_class":"P",
    "gn:feature_code":"PPL",
    "gn:name":"Oulad Messaouda",
    "gn:population":0,
    "gn:timezone":"Africa/Tunis",
    "iso:country":"TN",
    "wof:name":"Oulad Messaouda",
    "wof:placetype":"locality"
},
  "geometry": {"coordinates":[10.31778,36.03694],"type":"Point"}
}