{
  "type": "Feature",
  "properties": {
    "gn:admin1_code":"00",
    "gn:asciiname":"Sidi et Tarhouni",
    "gn:country_code":"TN",
    "gn:dem":258,
    "gn:feature_class":"P",
    "gn:feature_code":"PPL",
    "gn:name":"Sidi et Tarhouni",
    "gn:population":0,
    "gn:timezone":"Africa/Tunis",
    "iso:country":"TN",
    "name:und_x_variant":[
        "Sidi el Tarhouni",
        "Sidi et Tarhouni",
        "S\u012bd\u012b a\u0163 \u0162arh\u016bn\u012b"
    ],
    "wof:name":"Sidi et Tarhouni",
    "wof:placetype":"locality"
},
  "geometry": {"coordinates":[9.05,36.71667],"type":"Point"}
}