{
  "type": "Feature",
  "properties": {
    "gn:admin1_code":"14",
    "gn:asciiname":"Douar el Debabsa",
    "gn:country_code":"TN",
    "gn:dem":632,
    "gn:feature_class":"P",
    "gn:feature_code":"PPL",
    "gn:name":"Douar el Debabsa",
    "gn:population":0,
    "gn:timezone":"Africa/Tunis",
    "iso:country":"TN",
    "wof:name":"Douar el Debabsa",
    "wof:placetype":"locality"
},
  "geometry": {"coordinates":[9.11806,35.96694],"type":"Point"}
}