{
  "type": "Feature",
  "properties": {
    "gn:admin1_code":"00",
    "gn:asciiname":"Chemtou Ance",
    "gn:country_code":"TN",
    "gn:dem":161,
    "gn:feature_class":"P",
    "gn:feature_code":"PPL",
    "gn:name":"Chemtou Ance",
    "gn:population":0,
    "gn:timezone":"Africa/Tunis",
    "iso:country":"TN",
    "name:und_x_variant":[
        "Simittu",
        "Shim\u0163\u016b"
    ],
    "wof:name":"Chemtou Ance",
    "wof:placetype":"locality"
},
  "geometry": {"coordinates":[8.58333,36.48333],"type":"Point"}
}