{
  "type": "Feature",
  "properties": {
    "gn:admin1_code":"00",
    "gn:asciiname":"Hennchir Ksar Rhaleb",
    "gn:country_code":"TN",
    "gn:dem":19,
    "gn:feature_class":"P",
    "gn:feature_code":"PPL",
    "gn:name":"Hennchir Ksar Rhaleb",
    "gn:population":0,
    "gn:timezone":"Africa/Tunis",
    "iso:country":"TN",
    "name:und_x_variant":[
        "Hansh\u012br Qa\u015fr Ghall\u0101b"
    ],
    "wof:lang_x_official":[
        "ara",
        "fra"
    ],
    "wof:lang_x_spoken":[
        "ara",
        "fra"
    ],
    "wof:name":"Hennchir Ksar Rhaleb",
    "wof:placetype":"locality"
},
  "geometry": {"coordinates":[11.05,36.98333],"type":"Point"}
}