{
  "type": "Feature",
  "properties": {
    "gn:admin1_code":"03",
    "gn:asciiname":"Douar Tell er Rebia",
    "gn:country_code":"TN",
    "gn:dem":445,
    "gn:feature_class":"P",
    "gn:feature_code":"PPL",
    "gn:name":"Douar Tell er Rebia",
    "gn:population":0,
    "gn:timezone":"Africa/Tunis",
    "iso:country":"TN",
    "wof:name":"Douar Tell er Rebia",
    "wof:placetype":"locality"
},
  "geometry": {"coordinates":[9.60972,35.895],"type":"Point"}
}