{
  "type": "Feature",
  "properties": {
    "gn:admin1_code":"15",
    "gn:asciiname":"Douar Mabrouk Ben Rehem",
    "gn:country_code":"TN",
    "gn:dem":69,
    "gn:feature_class":"P",
    "gn:feature_code":"PPL",
    "gn:name":"Douar Mabrouk Ben Rehem",
    "gn:population":0,
    "gn:timezone":"Africa/Tunis",
    "iso:country":"TN",
    "wof:name":"Douar Mabrouk Ben Rehem",
    "wof:placetype":"locality"
},
  "geometry": {"coordinates":[10.23,35.33972],"type":"Point"}
}