{
  "type": "Feature",
  "properties": {
    "gn:admin1_code":"28",
    "gn:asciiname":"El Guecheine",
    "gn:country_code":"TN",
    "gn:dem":22,
    "gn:feature_class":"P",
    "gn:feature_code":"PPL",
    "gn:name":"El Gueche\u00efne",
    "gn:population":0,
    "gn:timezone":"Africa/Tunis",
    "iso:country":"TN",
    "name:und_x_variant":[
        "Guecha\u00efne",
        "El Gueche\u00efne"
    ],
    "wof:name":"El Guecheine",
    "wof:placetype":"locality"
},
  "geometry": {"coordinates":[10.90793,33.83573],"type":"Point"}
}