{
  "type": "Feature",
  "properties": {
    "gn:admin1_code":"16",
    "gn:asciiname":"Zaouiet Kountech",
    "gn:country_code":"TN",
    "gn:dem":26,
    "gn:feature_class":"P",
    "gn:feature_code":"PPL",
    "gn:name":"Zaouiet Kountech",
    "gn:population":0,
    "gn:timezone":"Africa/Tunis",
    "iso:country":"TN",
    "name:ara_x_preferred":[
        "\u0632\u0627\u0648\u064a\u0629 \u0642\u0646\u0637\u0634"
    ],
    "name:fra_x_preferred":[
        "Zaouiet Kontoch"
    ],
    "name:ukr_x_preferred":[
        "\u0417\u0430\u0443\u0432'\u0454\u0442-\u041a\u043e\u043d\u0442\u0435\u0448"
    ],
    "name:und_x_variant":[
        "Z\u0101wiyat Qun\u0163ash"
    ],
    "wof:lang_x_official":[
        "ara",
        "fra"
    ],
    "wof:lang_x_spoken":[
        "ara",
        "fra"
    ],
    "wof:name":"Zaouiet Kountech",
    "wof:placetype":"locality"
},
  "geometry": {"coordinates":[10.76667,35.63333],"type":"Point"}
}