{
  "type": "Feature",
  "properties": {
    "gn:admin1_code":"32",
    "gn:asciiname":"Sakiet ed Daier",
    "gn:cc2":"TN",
    "gn:country_code":"TN",
    "gn:dem":12,
    "gn:feature_class":"P",
    "gn:feature_code":"PPL",
    "gn:name":"Sakiet ed Daier",
    "gn:population":0,
    "gn:timezone":"Africa/Tunis",
    "iso:country":"TN",
    "name:ara_x_preferred":[
        "\u0633\u0627\u0642\u064a\u0629 \u0627\u0644\u062f\u0627\u0626\u0631"
    ],
    "name:cat_x_preferred":[
        "Sakiet Eddaier"
    ],
    "name:fra_x_preferred":[
        "Sakiet Edda\u00efer"
    ],
    "name:ukr_x_preferred":[
        "\u0421\u0430\u043a'\u0454\u0442-\u0435\u0434-\u0414\u0430\u0435\u0440"
    ],
    "name:und_x_variant":[
        "S\u0101qiyat ad D\u0101\u2019ir",
        "Sakiet ed Da\u00efr",
        "Sakiet ed Daier"
    ],
    "name:urd_x_preferred":[
        "\u0633\u0627\u0642\u06cc\u06c3 \u0627\u0644\u062f\u0627\u0626\u0631"
    ],
    "wof:name":"Sakiet ed Daier",
    "wof:placetype":"locality"
},
  "geometry": {"coordinates":[10.80617,34.79435],"type":"Point"}
}