{
  "type": "Feature",
  "properties": {
    "gn:admin1_code":"18",
    "gn:asciiname":"Douar Hammar el Hattab",
    "gn:country_code":"TN",
    "gn:dem":32,
    "gn:feature_class":"P",
    "gn:feature_code":"PPL",
    "gn:name":"Douar Hammar el Hattab",
    "gn:population":0,
    "gn:timezone":"Africa/Tunis",
    "iso:country":"TN",
    "wof:name":"Douar Hammar el Hattab",
    "wof:placetype":"locality"
},
  "geometry": {"coordinates":[9.70482,37.02465],"type":"Point"}
}