{
  "type": "Feature",
  "properties": {
    "gn:admin1_code":"02",
    "gn:asciiname":"Djar el Amri",
    "gn:country_code":"TN",
    "gn:dem":700,
    "gn:feature_class":"P",
    "gn:feature_code":"PPL",
    "gn:name":"Djar el Amri",
    "gn:population":0,
    "gn:timezone":"Africa/Tunis",
    "iso:country":"TN",
    "name:und_x_variant":[
        "Diar el Amri",
        "Djar el Amri",
        "Djar al Amri"
    ],
    "wof:name":"Djar el Amri",
    "wof:placetype":"locality"
},
  "geometry": {"coordinates":[8.56667,35.63333],"type":"Point"}
}