{
  "type": "Feature",
  "properties": {
    "gn:admin1_code":"36",
    "gn:asciiname":"Borj Oulad Lara",
    "gn:cc2":"TN",
    "gn:country_code":"TN",
    "gn:dem":7,
    "gn:feature_class":"P",
    "gn:feature_code":"PPL",
    "gn:name":"Borj Oulad Lara",
    "gn:population":0,
    "gn:timezone":"Africa/Tunis",
    "iso:country":"TN",
    "name:und_x_variant":[
        "Bordj Oulad Lara",
        "Borj Oulad Lara"
    ],
    "wof:name":"Borj Oulad Lara",
    "wof:placetype":"locality"
},
  "geometry": {"coordinates":[10.3225,36.8375],"type":"Point"}
}