{
  "type": "Feature",
  "properties": {
    "gn:admin1_code":"00",
    "gn:asciiname":"Cheguimi",
    "gn:country_code":"TN",
    "gn:dem":585,
    "gn:feature_class":"P",
    "gn:feature_code":"PPL",
    "gn:name":"Cheguimi",
    "gn:population":0,
    "gn:timezone":"Africa/Tunis",
    "iso:country":"TN",
    "name:und_x_variant":[
        "Shaq\u012bm\u012b"
    ],
    "wof:lang_x_official":[
        "ara",
        "fra"
    ],
    "wof:lang_x_spoken":[
        "ara",
        "fra"
    ],
    "wof:name":"Cheguimi",
    "wof:placetype":"locality"
},
  "geometry": {"coordinates":[10.13477,33.38978],"type":"Point"}
}