{
  "type": "Feature",
  "properties": {
    "gn:country":"TN",
    "gn:fcode":"PPL",
    "gn:pop":6047,
    "iso:country":"TN",
    "name:ara_x_preferred":[
        "\u0627\u0644\u0628\u0637\u0627\u0646"
    ],
    "name:cat_x_preferred":[
        "El Battan"
    ],
    "name:ceb_x_preferred":[
        "El Battan"
    ],
    "name:eng_x_preferred":[
        "El Battan"
    ],
    "name:fra_x_preferred":[
        "El Batan"
    ],
    "name:ukr_x_preferred":[
        "\u0415\u043b\u044c-\u0411\u0430\u0442\u0442\u0430\u043d"
    ],
    "name:unk_x_variant":[
        "Al Ba\u0163\u0101n"
    ],
    "qs:name":"El Battan",
    "qs:photos_9r":0,
    "qs:photos_sr":0,
    "qs:pop_sr":"5",
    "wd:wordcount":52,
    "wof:name":"El Battan",
    "wof:placetype":"locality",
    "wof:population":6047
},
  "geometry": {"coordinates":[9.84424,36.80368],"type":"Point"}
}