{
  "type": "Feature",
  "properties": {
    "gn:admin1_code":"31",
    "gn:asciiname":"Douar el Ma",
    "gn:country_code":"TN",
    "gn:dem":44,
    "gn:feature_class":"P",
    "gn:feature_code":"PPL",
    "gn:name":"Douar el Ma",
    "gn:population":0,
    "gn:timezone":"Africa/Tunis",
    "iso:country":"TN",
    "name:und_x_variant":[
        "Daww\u0101r al M\u0101\u2019"
    ],
    "wof:name":"Douar el Ma",
    "wof:placetype":"locality"
},
  "geometry": {"coordinates":[7.75,33.38333],"type":"Point"}
}