{
  "type": "Feature",
  "properties": {
    "gn:admin1_code":"00",
    "gn:asciiname":"Dar el Koudia",
    "gn:country_code":"TN",
    "gn:dem":22,
    "gn:feature_class":"P",
    "gn:feature_code":"PPL",
    "gn:name":"Dar el Koudia",
    "gn:population":0,
    "gn:timezone":"Africa/Tunis",
    "iso:country":"TN",
    "name:und_x_variant":[
        "Koudiat",
        "Kudiat",
        "Z\u0327ahr al Kudyah",
        "Dar el Koudia"
    ],
    "wof:name":"Dar el Koudia",
    "wof:placetype":"locality"
},
  "geometry": {"coordinates":[9.85959,37.28925],"type":"Point"}
}