{
  "type": "Feature",
  "properties": {
    "gn:admin1_code":"18",
    "gn:asciiname":"Douar el Mejoub",
    "gn:cc2":"TN",
    "gn:country_code":"TN",
    "gn:dem":161,
    "gn:feature_class":"P",
    "gn:feature_code":"PPL",
    "gn:name":"Douar el Mejoub",
    "gn:population":0,
    "gn:timezone":"Africa/Tunis",
    "iso:country":"TN",
    "name:und_x_variant":[
        "Douar el Medjoub",
        "Douar el Mejoub"
    ],
    "wof:name":"Douar el Mejoub",
    "wof:placetype":"locality"
},
  "geometry": {"coordinates":[9.90417,37.10056],"type":"Point"}
}