{
  "type": "Feature",
  "properties": {
    "gn:admin1_code":"18",
    "gn:asciiname":"Douar el Mabtouha",
    "gn:cc2":"TN",
    "gn:country_code":"TN",
    "gn:dem":7,
    "gn:feature_class":"P",
    "gn:feature_code":"PPL",
    "gn:name":"Douar el Mabtouha",
    "gn:population":0,
    "gn:timezone":"Africa/Tunis",
    "iso:country":"TN",
    "name:und_x_variant":[
        "Daww\u0101r al Mab\u0163\u016b\u1e29ah",
        "Douar el Mabtouha"
    ],
    "wof:name":"Douar el Mabtouha",
    "wof:placetype":"locality"
},
  "geometry": {"coordinates":[9.94861,36.96528],"type":"Point"}
}