{
  "type": "Feature",
  "properties": {
    "gn:admin1_code":"30",
    "gn:asciiname":"Lalla",
    "gn:country_code":"TN",
    "gn:dem":271,
    "gn:feature_class":"P",
    "gn:feature_code":"PPL",
    "gn:name":"Lalla",
    "gn:population":0,
    "gn:timezone":"Africa/Tunis",
    "iso:country":"TN",
    "name:deu_x_preferred":[
        "Lalla"
    ],
    "name:hat_x_preferred":[
        "Lalla"
    ],
    "name:hin_x_preferred":[
        "\u0932\u0932\u094d\u0932"
    ],
    "name:und_x_variant":[
        "Le\u00efla",
        "Ksar de Lala",
        "L\u0101llah",
        "Lala"
    ],
    "wof:name":"Lalla",
    "wof:placetype":"locality"
},
  "geometry": {"coordinates":[8.82084,34.39203],"type":"Point"}
}