{
  "type": "Feature",
  "properties": {
    "gn:admin1_code":"37",
    "gn:asciiname":"El M'nagha",
    "gn:country_code":"TN",
    "gn:dem":184,
    "gn:feature_class":"P",
    "gn:feature_code":"PPL",
    "gn:name":"El M\u2019nagha",
    "gn:population":0,
    "gn:timezone":"Africa/Tunis",
    "iso:country":"TN",
    "wof:name":"El M'nagha",
    "wof:placetype":"locality"
},
  "geometry": {"coordinates":[9.945,36.55278],"type":"Point"}
}