{
  "type": "Feature",
  "properties": {
    "gn:admin1_code":"39",
    "gn:asciiname":"Douar el Haim",
    "gn:country_code":"TN",
    "gn:dem":57,
    "gn:feature_class":"P",
    "gn:feature_code":"PPL",
    "gn:name":"Douar el Ha\u00efm",
    "gn:population":0,
    "gn:timezone":"Africa/Tunis",
    "iso:country":"TN",
    "wof:name":"Douar el Haim",
    "wof:placetype":"locality"
},
  "geometry": {"coordinates":[9.86278,36.70278],"type":"Point"}
}