{
  "type": "Feature",
  "properties": {
    "gn:admin1_code":"03",
    "gn:asciiname":"Dar Bel Kassem Bou Ktel",
    "gn:country_code":"TN",
    "gn:dem":118,
    "gn:feature_class":"P",
    "gn:feature_code":"PPL",
    "gn:name":"Dar Bel Kassem Bou Ktel",
    "gn:population":0,
    "gn:timezone":"Africa/Tunis",
    "iso:country":"TN",
    "wof:name":"Dar Bel Kassem Bou Ktel",
    "wof:placetype":"locality"
},
  "geometry": {"coordinates":[10.13917,35.31028],"type":"Point"}
}