{
  "type": "Feature",
  "properties": {
    "gn:admin1_code":"22",
    "gn:asciiname":"Dechret Sefaieb",
    "gn:cc2":"TN",
    "gn:country_code":"TN",
    "gn:dem":646,
    "gn:feature_class":"P",
    "gn:feature_code":"PPL",
    "gn:name":"Dechret Sefa\u00efeb",
    "gn:population":0,
    "gn:timezone":"Africa/Tunis",
    "iso:country":"TN",
    "name:und_x_variant":[
        "Dashrat Sefa\u00efeb",
        "Dechret Sefa\u00efeb"
    ],
    "wof:name":"Dechret Sefaieb",
    "wof:placetype":"locality"
},
  "geometry": {"coordinates":[9.10556,35.66222],"type":"Point"}
}