{
  "type": "Feature",
  "properties": {
    "gn:admin1_code":"19",
    "gn:asciiname":"Segermes",
    "gn:country_code":"TN",
    "gn:dem":50,
    "gn:feature_class":"P",
    "gn:feature_code":"PPL",
    "gn:name":"Segermes",
    "gn:population":0,
    "gn:timezone":"Africa/Tunis",
    "iso:country":"TN",
    "name:ara_x_preferred":[
        "\u0633\u062c\u0631\u0645\u0627\u0633"
    ],
    "name:deu_x_preferred":[
        "Titularbistum Segermes"
    ],
    "name:pol_x_preferred":[
        "Segermes"
    ],
    "name:rus_x_preferred":[
        "\u0415\u043f\u0430\u0440\u0445\u0438\u044f \u0421\u0435\u0433\u0435\u0440\u043c\u044b"
    ],
    "wof:name":"Segermes",
    "wof:placetype":"locality"
},
  "geometry": {"coordinates":[10.34167,36.34],"type":"Point"}
}