{
  "type": "Feature",
  "properties": {
    "gn:admin1_code":"00",
    "gn:asciiname":"Sidi Bou Rouis",
    "gn:country_code":"TN",
    "gn:dem":406,
    "gn:feature_class":"P",
    "gn:feature_code":"PPL",
    "gn:name":"Sidi Bou Rouis",
    "gn:population":0,
    "gn:timezone":"Africa/Tunis",
    "iso:country":"TN",
    "name:und_x_variant":[
        "S\u012bd\u012b B\u016b Ru\u2019ays"
    ],
    "wof:name":"Sidi Bou Rouis",
    "wof:placetype":"locality"
},
  "geometry": {"coordinates":[9.1235,36.17665],"type":"Point"}
}