{
  "type": "Feature",
  "properties": {
    "gn:admin1_code":"00",
    "gn:asciiname":"Sidi Bou Rouis",
    "gn:country_code":"TN",
    "gn:dem":406,
    "gn:feature_class":"P",
    "gn:feature_code":"PPL",
    "gn:name":"Sidi Bou Rouis",
    "gn:population":0,
    "gn:timezone":"Africa/Tunis",
    "iso:country":"TN",
    "name:ara_x_preferred":[
        "\u0633\u064a\u062f\u064a \u0628\u0648\u0631\u0648\u064a\u0633"
    ],
    "name:cat_x_preferred":[
        "Bourouis"
    ],
    "name:ceb_x_preferred":[
        "S\u012bd\u012b B\u016b Ru'ays"
    ],
    "name:fra_x_preferred":[
        "Sidi Bou Rouis"
    ],
    "name:ukr_x_preferred":[
        "\u0421\u0456\u0434\u0456-\u0411\u0443\u0440\u0443\u0457\u0441"
    ],
    "name:und_x_variant":[
        "S\u012bd\u012b B\u016b Ru\u2019ays"
    ],
    "wof:name":"Sidi Bou Rouis",
    "wof:placetype":"locality"
},
  "geometry": {"coordinates":[9.1235,36.17665],"type":"Point"}
}