{
  "type": "Feature",
  "properties": {
    "gn:admin1_code":"03",
    "gn:asciiname":"Douar Chaib",
    "gn:cc2":"TN",
    "gn:country_code":"TN",
    "gn:dem":470,
    "gn:feature_class":"P",
    "gn:feature_code":"PPL",
    "gn:name":"Douar Cha\u00efb",
    "gn:population":0,
    "gn:timezone":"Africa/Tunis",
    "iso:country":"TN",
    "name:und_x_variant":[
        "Daww\u0101r Sha\u2018\u012bb",
        "Douar Cha\u00efb"
    ],
    "wof:name":"Douar Chaib",
    "wof:placetype":"locality"
},
  "geometry": {"coordinates":[9.54694,35.75889],"type":"Point"}
}