{
  "type": "Feature",
  "properties": {
    "gn:admin1_code":"36",
    "gn:asciiname":"Fath Allah",
    "gn:cc2":"TN",
    "gn:country_code":"TN",
    "gn:dem":6,
    "gn:feature_class":"P",
    "gn:feature_code":"PPL",
    "gn:name":"Fath Allah",
    "gn:population":0,
    "gn:timezone":"Africa/Tunis",
    "iso:country":"TN",
    "name:und_x_variant":[
        "S\u012bd\u012b Fat\u1e29 All\u0101h",
        "Fath Allah"
    ],
    "wof:name":"Fath Allah",
    "wof:placetype":"locality"
},
  "geometry": {"coordinates":[10.20944,36.76806],"type":"Point"}
}