{
  "type": "Feature",
  "properties": {
    "gn:admin1_code":"32",
    "gn:asciiname":"Douar ez Zergane",
    "gn:country_code":"TN",
    "gn:dem":126,
    "gn:feature_class":"P",
    "gn:feature_code":"PPL",
    "gn:name":"Douar ez Zergane",
    "gn:population":0,
    "gn:timezone":"Africa/Tunis",
    "iso:country":"TN",
    "wof:name":"Douar ez Zergane",
    "wof:placetype":"locality"
},
  "geometry": {"coordinates":[10.47111,34.76667],"type":"Point"}
}