{
  "type": "Feature",
  "properties": {
    "gn:admin1_code":"06",
    "gn:asciiname":"Ain Bou Seba",
    "gn:country_code":"TN",
    "gn:dem":840,
    "gn:feature_class":"P",
    "gn:feature_code":"PPL",
    "gn:name":"A\u00efn Bou Seba",
    "gn:population":0,
    "gn:timezone":"Africa/Tunis",
    "iso:country":"TN",
    "wof:name":"Ain Bou Seba",
    "wof:placetype":"locality"
},
  "geometry": {"coordinates":[8.45083,36.27889],"type":"Point"}
}