{
  "type": "Feature",
  "properties": {
    "iso:country":"TN",
    "name:ara_x_preferred":[
        "Le Passage"
    ],
    "name:ceb_x_preferred":[
        "Le Passage"
    ],
    "name:deu_x_preferred":[
        "Le Passage"
    ],
    "name:fra_x_preferred":[
        "Le Passage"
    ],
    "name:ita_x_preferred":[
        "Le Passage"
    ],
    "name:nds_x_preferred":[
        "Le Passage"
    ],
    "name:nld_x_preferred":[
        "Le Passage"
    ],
    "name:pms_x_preferred":[
        "Le Passage"
    ],
    "name:pol_x_preferred":[
        "Le Passage"
    ],
    "name:por_x_preferred":[
        "Le Passage"
    ],
    "name:slk_x_preferred":[
        "Le Passage"
    ],
    "name:spa_x_preferred":[
        "Le Passage"
    ],
    "name:swe_x_preferred":[
        "Le Passage"
    ],
    "qs:gn_adm0_cc":"TN",
    "qs:gn_local":2464470,
    "qs:gn_nam_loc":"\u062a\u0648\u0646\u0633, Tunis, TN",
    "qs:gn_namadm1":"36",
    "qs:local_max":1018,
    "qs:local_sum":7193,
    "qs:localhoods":20,
    "qs:name":"Le Passage",
    "qs:name_adm0":"Tunisia",
    "qs:name_adm1":"Tunis",
    "qs:name_local":"\u062a\u0648\u0646\u0633",
    "qs:photo_max":97,
    "qs:photo_sum":237,
    "qs:placetype":"Suburb",
    "qs:quad_count":8,
    "qs:woe_adm0":23424967,
    "qs:woe_adm1":2347256,
    "qs:woe_adm2":0,
    "qs:woe_lau":0,
    "qs:woe_local":1442746,
    "qs:woe_ver":"7.10.0",
    "wof:name":"Le Passage",
    "wof:placetype":"neighbourhood"
},
  "geometry": {"coordinates":[10.182384,36.805207],"type":"Point"}
}