{
  "type": "Feature",
  "properties": {
    "gn:admin1_code":"00",
    "gn:asciiname":"El Bekakcha",
    "gn:country_code":"TN",
    "gn:dem":116,
    "gn:feature_class":"P",
    "gn:feature_code":"PPL",
    "gn:name":"El Bekakcha",
    "gn:population":0,
    "gn:timezone":"Africa/Tunis",
    "iso:country":"TN",
    "name:und_x_variant":[
        "Al Bak\u0101kishah"
    ],
    "wof:name":"El Bekakcha",
    "wof:placetype":"locality"
},
  "geometry": {"coordinates":[10.65,36.83333],"type":"Point"}
}