{
  "type": "Feature",
  "properties": {
    "gn:admin1_code":"18",
    "gn:asciiname":"Douar Lezdine",
    "gn:cc2":"TN",
    "gn:country_code":"TN",
    "gn:dem":10,
    "gn:feature_class":"P",
    "gn:feature_code":"PPL",
    "gn:name":"Douar Lezdine",
    "gn:population":0,
    "gn:timezone":"Africa/Tunis",
    "iso:country":"TN",
    "name:und_x_variant":[
        "Daww\u0101r Lezdine",
        "Douar Lezdine"
    ],
    "wof:name":"Douar Lezdine",
    "wof:placetype":"locality"
},
  "geometry": {"coordinates":[10.0075,36.94611],"type":"Point"}
}