{
  "type": "Feature",
  "properties": {
    "gn:admin1_code":"28",
    "gn:asciiname":"Bordj Sidi Toui",
    "gn:country_code":"TN",
    "gn:dem":38,
    "gn:feature_class":"P",
    "gn:feature_code":"PPL",
    "gn:name":"Bordj Sidi Toui",
    "gn:population":0,
    "gn:timezone":"Africa/Tunis",
    "iso:country":"TN",
    "name:und_x_variant":[
        "Sidi Touil",
        "Bordj Sidi Toui",
        "Burj S\u012bd\u012b a\u0163 \u0162aw\u012b",
        "Borj Sidi Toui"
    ],
    "wof:lang_x_official":[
        "ara",
        "fra"
    ],
    "wof:lang_x_spoken":[
        "ara",
        "fra"
    ],
    "wof:name":"Bordj Sidi Toui",
    "wof:placetype":"locality"
},
  "geometry": {"coordinates":[11.36941,32.72634],"type":"Point"}
}