{
  "type": "Feature",
  "properties": {
    "gn:admin1_code":"00",
    "gn:asciiname":"Beni Ata",
    "gn:country_code":"TN",
    "gn:dem":44,
    "gn:feature_class":"P",
    "gn:feature_code":"PPL",
    "gn:name":"Beni Ata",
    "gn:population":0,
    "gn:timezone":"Africa/Tunis",
    "iso:country":"TN",
    "name:und_x_variant":[
        "Beni Eta",
        "Ban\u012b \u2018A\u0163\u0101\u2019"
    ],
    "wof:name":"Beni Ata",
    "wof:placetype":"locality"
},
  "geometry": {"coordinates":[10.07957,37.23033],"type":"Point"}
}