{
  "type": "Feature",
  "properties": {
    "gn:admin1_code":"31",
    "gn:asciiname":"Mennchia",
    "gn:cc2":"TN",
    "gn:country_code":"TN",
    "gn:dem":47,
    "gn:feature_class":"P",
    "gn:feature_code":"PPL",
    "gn:name":"Mennchia",
    "gn:population":0,
    "gn:timezone":"Africa/Tunis",
    "iso:country":"TN",
    "name:und_x_variant":[
        "Mansh\u012byah",
        "Menchia",
        "Mennchia"
    ],
    "wof:lang_x_official":[
        "ara",
        "fra"
    ],
    "wof:lang_x_spoken":[
        "ara",
        "fra"
    ],
    "wof:name":"Mennchia",
    "wof:placetype":"locality"
},
  "geometry": {"coordinates":[8.85583,33.78278],"type":"Point"}
}