{
  "type": "Feature",
  "properties": {
    "gn:admin1_code":"00",
    "gn:asciiname":"Douar Hammada",
    "gn:country_code":"TN",
    "gn:dem":131,
    "gn:feature_class":"P",
    "gn:feature_code":"PPL",
    "gn:name":"Douar Hammada",
    "gn:population":0,
    "gn:timezone":"Africa/Tunis",
    "iso:country":"TN",
    "name:und_x_variant":[
        "Daww\u0101r \u1e28amm\u0101dah"
    ],
    "wof:name":"Douar Hammada",
    "wof:placetype":"locality"
},
  "geometry": {"coordinates":[9.66667,37.31667],"type":"Point"}
}