{
  "type": "Feature",
  "properties": {
    "gn:admin1_code":"31",
    "gn:asciiname":"El Meghmouma",
    "gn:country_code":"TN",
    "gn:dem":36,
    "gn:feature_class":"P",
    "gn:feature_code":"PPL",
    "gn:name":"El Meghmouma",
    "gn:population":0,
    "gn:timezone":"Africa/Tunis",
    "iso:country":"TN",
    "name:und_x_variant":[
        "Al Maghm\u016bmah",
        "El Merhmouma",
        "El Meghmouma"
    ],
    "wof:name":"El Meghmouma",
    "wof:placetype":"locality"
},
  "geometry": {"coordinates":[8.88468,33.57074],"type":"Point"}
}