{
  "type": "Feature",
  "properties": {
    "gn:admin1_code":"00",
    "gn:asciiname":"Zaouiet Azmour",
    "gn:country_code":"TN",
    "gn:dem":55,
    "gn:feature_class":"P",
    "gn:feature_code":"PPL",
    "gn:name":"Zaouiet Azmour",
    "gn:population":0,
    "gn:timezone":"Africa/Tunis",
    "iso:country":"TN",
    "name:ceb_x_preferred":[
        "Z\u0101wiyat az Zum\u016br"
    ],
    "name:fra_x_preferred":[
        "Azmour"
    ],
    "name:ita_x_preferred":[
        "Azmour"
    ],
    "name:ukr_x_preferred":[
        "\u0410\u0437\u043c\u0443\u0440"
    ],
    "name:und_x_variant":[
        "Zaouiet Lazmour",
        "Z\u0101wiyat az Zum\u016br"
    ],
    "wof:name":"Zaouiet Azmour",
    "wof:placetype":"locality"
},
  "geometry": {"coordinates":[11.0078,36.92441],"type":"Point"}
}