{
  "type": "Feature",
  "properties": {
    "gn:admin1_code":"00",
    "gn:asciiname":"El Erijat",
    "gn:country_code":"TN",
    "gn:dem":167,
    "gn:feature_class":"P",
    "gn:feature_code":"PPL",
    "gn:name":"El Erijat",
    "gn:population":0,
    "gn:timezone":"Africa/Tunis",
    "iso:country":"TN",
    "wof:name":"El Erijat",
    "wof:placetype":"locality"
},
  "geometry": {"coordinates":[9.92611,35.1425],"type":"Point"}
}