{
  "type": "Feature",
  "properties": {
    "gn:country":"TN",
    "gn:fcode":"PPL",
    "gn:population":7189,
    "iso:country":"TN",
    "name:ara_x_preferred":[
        "\u0627\u0644\u0642\u0644\u0639\u0629"
    ],
    "name:cat_x_preferred":[
        "El Gol\u00e2a"
    ],
    "name:ceb_x_preferred":[
        "El Golaa"
    ],
    "name:eng_x_preferred":[
        "El Gol\u00e2a"
    ],
    "name:fas_x_preferred":[
        "\u0627\u0644\u0642\u0644\u0639\u0647"
    ],
    "name:fra_x_preferred":[
        "El Gol\u00e2a"
    ],
    "name:nld_x_preferred":[
        "El Gol\u00e2a"
    ],
    "name:por_x_preferred":[
        "El Gol\u00e2a"
    ],
    "name:sco_x_preferred":[
        "El Gol\u00e2a"
    ],
    "name:tur_x_preferred":[
        "El-Kale"
    ],
    "name:ukr_x_preferred":[
        "\u0415\u043b\u044c-\u041a\u0430\u043b\u044f\u0430"
    ],
    "name:und_x_variant":[
        "Galaa"
    ],
    "name:zul_x_preferred":[
        "El Gol\u00e2a"
    ],
    "qs:name":"El Golaa",
    "qs:photos_9r":0,
    "qs:photos_sr":0,
    "qs:pop_sr":"5",
    "wd:wordcount":225,
    "wof:name":"El Golaa",
    "wof:placetype":"locality",
    "wof:population":7189
},
  "geometry": {"coordinates":[9.00678,33.48485],"type":"Point"}
}