{
  "type": "Feature",
  "properties": {
    "gn:admin1_code":"16",
    "gn:asciiname":"Manzil Khayr",
    "gn:country_code":"TN",
    "gn:dem":47,
    "gn:feature_class":"P",
    "gn:feature_code":"PPL",
    "gn:name":"Manzil Khayr",
    "gn:population":0,
    "gn:timezone":"Africa/Tunis",
    "iso:country":"TN",
    "name:und_x_variant":[
        "Menzel Krir",
        "Menzel-Khir",
        "Manzil Khayr"
    ],
    "wof:lang_x_official":[
        "ara",
        "fra"
    ],
    "wof:lang_x_spoken":[
        "ara",
        "fra"
    ],
    "wof:name":"Manzil Khayr",
    "wof:placetype":"locality"
},
  "geometry": {"coordinates":[10.71125,35.69664],"type":"Point"}
}