{
  "type": "Feature",
  "properties": {
    "gn:admin1_code":"03",
    "gn:asciiname":"Koudiat ech Chouicha",
    "gn:country_code":"TN",
    "gn:dem":324,
    "gn:feature_class":"P",
    "gn:feature_code":"PPL",
    "gn:name":"Koudiat ech Chouicha",
    "gn:population":0,
    "gn:timezone":"Africa/Tunis",
    "iso:country":"TN",
    "wof:lang_x_official":[
        "ara",
        "fra"
    ],
    "wof:lang_x_spoken":[
        "ara",
        "fra"
    ],
    "wof:name":"Koudiat ech Chouicha",
    "wof:placetype":"locality"
},
  "geometry": {"coordinates":[9.64222,35.47562],"type":"Point"}
}