{
  "type": "Feature",
  "properties": {
    "gn:admin1_code":"19",
    "gn:asciiname":"Bou Chlaga",
    "gn:country_code":"TN",
    "gn:dem":243,
    "gn:feature_class":"P",
    "gn:feature_code":"PPL",
    "gn:name":"Bou Chlaga",
    "gn:population":0,
    "gn:timezone":"Africa/Tunis",
    "iso:country":"TN",
    "wof:name":"Bou Chlaga",
    "wof:placetype":"locality"
},
  "geometry": {"coordinates":[10.18833,36.54667],"type":"Point"}
}