{
  "type": "Feature",
  "properties": {
    "gn:admin1_code":"31",
    "gn:asciiname":"Berghoutsia",
    "gn:country_code":"TN",
    "gn:dem":39,
    "gn:feature_class":"P",
    "gn:feature_code":"PPL",
    "gn:name":"Berghoutsia",
    "gn:population":0,
    "gn:timezone":"Africa/Tunis",
    "iso:country":"TN",
    "name:und_x_variant":[
        "Burgh\u016bth\u012byah",
        "Barghouthla",
        "Berrboutsia",
        "Berrhoutsia",
        "Berghoutsia"
    ],
    "wof:name":"Berghoutsia",
    "wof:placetype":"locality"
},
  "geometry": {"coordinates":[8.91348,33.6039],"type":"Point"}
}