{
  "type": "Feature",
  "properties": {
    "gn:admin1_code":"31",
    "gn:asciiname":"Er Rahmat",
    "gn:country_code":"TN",
    "gn:dem":45,
    "gn:feature_class":"P",
    "gn:feature_code":"PPL",
    "gn:name":"Er Rahmat",
    "gn:population":0,
    "gn:timezone":"Africa/Tunis",
    "iso:country":"TN",
    "name:und_x_variant":[
        "Rahmat",
        "Ar Ra\u1e29m\u0101t",
        "Er Rahmat"
    ],
    "wof:name":"Er Rahmat",
    "wof:placetype":"locality"
},
  "geometry": {"coordinates":[8.99905,33.64386],"type":"Point"}
}