{
  "type": "Feature",
  "properties": {
    "gn:admin1_code":"02",
    "gn:asciiname":"Dechret Zaouiet Sidi Salah",
    "gn:country_code":"TN",
    "gn:dem":914,
    "gn:feature_class":"P",
    "gn:feature_code":"PPL",
    "gn:name":"Dechret Zaouiet Sidi Salah",
    "gn:population":0,
    "gn:timezone":"Africa/Tunis",
    "iso:country":"TN",
    "name:und_x_variant":[
        "Zaouiet Sidi Salah ben Jabar",
        "Zaouiet Sidi Salah Ben Djabar",
        "Zaouia Sidi Salah ben Jabar",
        "Dashrat Z\u0101wiyat S\u012bd\u012b \u015e\u0101li\u1e29"
    ],
    "wof:lang_x_official":[
        "ara",
        "fra"
    ],
    "wof:lang_x_spoken":[
        "ara",
        "fra"
    ],
    "wof:name":"Dechret Zaouiet Sidi Salah",
    "wof:placetype":"locality"
},
  "geometry": {"coordinates":[8.65971,35.15744],"type":"Point"}
}