{
  "type": "Feature",
  "properties": {
    "gn:admin1_code":"34",
    "gn:asciiname":"Ksar Mrabtine",
    "gn:country_code":"TN",
    "gn:dem":334,
    "gn:feature_class":"P",
    "gn:feature_code":"PPL",
    "gn:name":"Ksar Mrabtine",
    "gn:population":0,
    "gn:timezone":"Africa/Tunis",
    "iso:country":"TN",
    "name:und_x_variant":[
        "Qa\u015fr al Mur\u0101bi\u0163\u012bn",
        "Ksar Mrabtine"
    ],
    "wof:name":"Ksar Mrabtine",
    "wof:placetype":"locality"
},
  "geometry": {"coordinates":[10.37672,33.03163],"type":"Point"}
}