{
  "type": "Feature",
  "properties": {
    "gn:admin1_code":"00",
    "gn:asciiname":"El Aroussa",
    "gn:country_code":"TN",
    "gn:dem":179,
    "gn:feature_class":"P",
    "gn:feature_code":"PPL",
    "gn:name":"El Aroussa",
    "gn:population":0,
    "gn:timezone":"Africa/Tunis",
    "iso:country":"TN",
    "name:und_x_variant":[
        "El Arouna",
        "El Aroussa",
        "Al \u2018Ar\u016bsah"
    ],
    "wof:name":"El Aroussa",
    "wof:placetype":"locality"
},
  "geometry": {"coordinates":[9.45,36.38333],"type":"Point"}
}