{
  "type": "Feature",
  "properties": {
    "gn:admin1_code":"00",
    "gn:asciiname":"El Aroussa",
    "gn:country_code":"TN",
    "gn:dem":179,
    "gn:feature_class":"P",
    "gn:feature_code":"PPL",
    "gn:name":"El Aroussa",
    "gn:population":0,
    "gn:timezone":"Africa/Tunis",
    "iso:country":"TN",
    "name:ara_x_preferred":[
        "\u0627\u0644\u0639\u0631\u0648\u0633\u0629"
    ],
    "name:cat_x_preferred":[
        "Laroussa"
    ],
    "name:deu_x_preferred":[
        "El Aroussa"
    ],
    "name:fra_x_preferred":[
        "El Aroussa"
    ],
    "name:ukr_x_preferred":[
        "\u0415\u043b\u044c-\u0410\u0440\u0443\u0441\u0441\u0430"
    ],
    "name:und_x_variant":[
        "El Arouna",
        "Al \u2018Ar\u016bsah"
    ],
    "wof:lang_x_official":[
        "ara",
        "fra"
    ],
    "wof:lang_x_spoken":[
        "ara",
        "fra"
    ],
    "wof:name":"El Aroussa",
    "wof:placetype":"locality"
},
  "geometry": {"coordinates":[9.45,36.38333],"type":"Point"}
}