{
  "type": "Feature",
  "properties": {
    "gn:admin1_code":"03",
    "gn:asciiname":"Fondouk el Okbi",
    "gn:cc2":"TN",
    "gn:country_code":"TN",
    "gn:dem":210,
    "gn:feature_class":"P",
    "gn:feature_code":"PPL",
    "gn:name":"Fondouk el Okbi",
    "gn:population":0,
    "gn:timezone":"Africa/Tunis",
    "iso:country":"TN",
    "name:und_x_variant":[
        "Fondouk el Aouareb",
        "Fonndouk el Okbi",
        "Funduq al \u2018Uqb\u012b",
        "Fondouck el Oqbi",
        "Fondouk el Okbi"
    ],
    "wof:name":"Fondouk el Okbi",
    "wof:placetype":"locality"
},
  "geometry": {"coordinates":[9.75,35.56667],"type":"Point"}
}