{
  "type": "Feature",
  "properties": {
    "gn:admin1_code":"37",
    "gn:asciiname":"Moghrane",
    "gn:country_code":"TN",
    "gn:dem":157,
    "gn:feature_class":"P",
    "gn:feature_code":"PPL",
    "gn:name":"Moghrane",
    "gn:population":0,
    "gn:timezone":"Africa/Tunis",
    "iso:country":"TN",
    "name:und_x_variant":[
        "Morhrane",
        "Muqr\u0101n"
    ],
    "wof:name":"Moghrane",
    "wof:placetype":"locality"
},
  "geometry": {"coordinates":[10.08998,36.42148],"type":"Point"}
}