{
  "type": "Feature",
  "properties": {
    "iso:country":"TN",
    "qs:gn_pop":0,
    "qs:name":"Chatt Meriem",
    "qs:name_adm0":"Tunisia",
    "qs:name_adm1":"Susah",
    "qs:photos":140,
    "qs:photos_1k":28,
    "qs:photos_9k":1,
    "qs:photos_9r":3,
    "qs:photos_all":140,
    "qs:photos_sr":3,
    "qs:placetype":"Town",
    "qs:pop_sr":"0",
    "qs:woe_adm0":23424967,
    "wof:name":"Chatt Meriem",
    "wof:placetype":"locality"
},
  "geometry": {"coordinates":[10.526876,35.950296],"type":"Point"}
}