{
  "type": "Feature",
  "properties": {
    "gn:admin1_code":"23",
    "gn:asciiname":"Cite Ouvriere",
    "gn:country_code":"TN",
    "gn:dem":42,
    "gn:feature_class":"P",
    "gn:feature_code":"PPL",
    "gn:name":"Cit\u00e9 Ouvri\u00e8re",
    "gn:population":0,
    "gn:timezone":"Africa/Tunis",
    "iso:country":"TN",
    "wof:name":"Cite Ouvriere",
    "wof:placetype":"locality"
},
  "geometry": {"coordinates":[10.35062,36.14674],"type":"Point"}
}