{
  "type": "Feature",
  "properties": {
    "iso:country":"TN",
    "name:ara_x_preferred":[
        "\u0634\u0631\u0628\u0627\u0646"
    ],
    "name:cat_x_preferred":[
        "Chorbane"
    ],
    "name:ceb_x_preferred":[
        "Shurb\u0101n"
    ],
    "name:eng_x_preferred":[
        "Chorbane"
    ],
    "name:fra_x_preferred":[
        "Chorbane"
    ],
    "name:nld_x_preferred":[
        "Chorbane"
    ],
    "name:ron_x_preferred":[
        "Chorbane"
    ],
    "name:ukr_x_preferred":[
        "\u0428\u043e\u0440\u0431\u0430\u043d"
    ],
    "name:unk_x_variant":[
        "Chourbane"
    ],
    "qs:gn_country":"TN",
    "qs:gn_fcode":"PPL",
    "qs:gn_pop":6430,
    "qs:name":"Shurban",
    "qs:name_adm0":"Tunisia",
    "qs:name_adm1":"Al Mahdiyah",
    "qs:photos":0,
    "qs:photos_1k":0,
    "qs:photos_9k":0,
    "qs:photos_9r":0,
    "qs:photos_all":0,
    "qs:photos_sr":0,
    "qs:placetype":"Town",
    "qs:pop_sr":"5",
    "qs:woe_adm0":23424967,
    "wd:wordcount":42,
    "wof:name":"Shurban",
    "wof:placetype":"locality",
    "wof:population":6430
},
  "geometry": {"coordinates":[10.3858,35.28581],"type":"Point"}
}