{
  "type": "Feature",
  "properties": {
    "gn:admin1_code":"29",
    "gn:asciiname":"El Argoub",
    "gn:country_code":"TN",
    "gn:dem":356,
    "gn:feature_class":"P",
    "gn:feature_code":"PPL",
    "gn:name":"El Argoub",
    "gn:population":0,
    "gn:timezone":"Africa/Tunis",
    "iso:country":"TN",
    "name:und_x_variant":[
        "Al \u2018Urq\u016bb"
    ],
    "wof:name":"El Argoub",
    "wof:placetype":"locality"
},
  "geometry": {"coordinates":[10.05,33.55],"type":"Point"}
}