{
  "type": "Feature",
  "properties": {
    "gn:admin1_code":"29",
    "gn:asciiname":"El Argoub",
    "gn:country_code":"TN",
    "gn:dem":356,
    "gn:feature_class":"P",
    "gn:feature_code":"PPL",
    "gn:name":"El Argoub",
    "gn:population":0,
    "gn:timezone":"Africa/Tunis",
    "iso:country":"TN",
    "name:ara_x_preferred":[
        "\u0627\u0644\u0639\u0631\u0643\u0648\u0628"
    ],
    "name:bar_x_preferred":[
        "El Argoub"
    ],
    "name:bul_x_preferred":[
        "\u0410\u0440\u0433\u0443\u0431"
    ],
    "name:cat_x_preferred":[
        "Argub"
    ],
    "name:deu_x_preferred":[
        "El Argoub"
    ],
    "name:fra_x_preferred":[
        "El Argoub"
    ],
    "name:ita_x_preferred":[
        "El Argoub"
    ],
    "name:und_x_variant":[
        "Al \u2018Urq\u016bb"
    ],
    "wof:name":"El Argoub",
    "wof:placetype":"locality"
},
  "geometry": {"coordinates":[10.05,33.55],"type":"Point"}
}