{
  "type": "Feature",
  "properties": {
    "gn:admin1_code":"18",
    "gn:asciiname":"Douar Otsmane",
    "gn:country_code":"TN",
    "gn:dem":192,
    "gn:feature_class":"P",
    "gn:feature_code":"PPL",
    "gn:name":"Douar Otsmane",
    "gn:population":0,
    "gn:timezone":"Africa/Tunis",
    "iso:country":"TN",
    "wof:name":"Douar Otsmane",
    "wof:placetype":"locality"
},
  "geometry": {"coordinates":[9.91139,37.06528],"type":"Point"}
}