{
  "type": "Feature",
  "properties": {
    "gn:admin1_code":"18",
    "gn:asciiname":"Douar Hassine Ben Haj Salah",
    "gn:country_code":"TN",
    "gn:dem":15,
    "gn:feature_class":"P",
    "gn:feature_code":"PPL",
    "gn:name":"Douar Hassine Ben Haj Salah",
    "gn:population":0,
    "gn:timezone":"Africa/Tunis",
    "iso:country":"TN",
    "name:und_x_variant":[
        "Douar Hassine Ben Hadj Salah",
        "Douar Hassine Ben Haj Salah"
    ],
    "wof:name":"Douar Hassine Ben Haj Salah",
    "wof:placetype":"locality"
},
  "geometry": {"coordinates":[9.68592,37.18616],"type":"Point"}
}