{
  "type": "Feature",
  "properties": {
    "gn:admin1_code":"34",
    "gn:asciiname":"Ksar Chouline",
    "gn:country_code":"TN",
    "gn:dem":226,
    "gn:feature_class":"P",
    "gn:feature_code":"PPL",
    "gn:name":"Ksar Chouline",
    "gn:population":0,
    "gn:timezone":"Africa/Tunis",
    "iso:country":"TN",
    "name:und_x_variant":[
        "Qa\u015fr Chouline"
    ],
    "wof:name":"Ksar Chouline",
    "wof:placetype":"locality"
},
  "geometry": {"coordinates":[10.43333,33.03333],"type":"Point"}
}