{
  "type": "Feature",
  "properties": {
    "gn:admin1_code":"00",
    "gn:asciiname":"Dar Hassen Zegoulli",
    "gn:country_code":"TN",
    "gn:dem":71,
    "gn:feature_class":"P",
    "gn:feature_code":"PPL",
    "gn:name":"Dar Hassen Zegoulli",
    "gn:population":0,
    "gn:timezone":"Africa/Tunis",
    "iso:country":"TN",
    "name:und_x_variant":[
        "D\u0101r \u1e28asan Zegoulli",
        "Dar Hassen Zegouli",
        "Dar Hassen Zegoulli"
    ],
    "wof:lang_x_official":[
        "ara",
        "fra"
    ],
    "wof:lang_x_spoken":[
        "ara",
        "fra"
    ],
    "wof:name":"Dar Hassen Zegoulli",
    "wof:placetype":"locality"
},
  "geometry": {"coordinates":[10.79052,36.66127],"type":"Point"}
}