{
  "type": "Feature",
  "properties": {
    "gn:admin1_code":"35",
    "gn:asciiname":"Chabbia",
    "gn:country_code":"TN",
    "gn:dem":76,
    "gn:feature_class":"P",
    "gn:feature_code":"PPL",
    "gn:name":"Chabbia",
    "gn:population":0,
    "gn:timezone":"Africa/Tunis",
    "iso:country":"TN",
    "wof:name":"Chabbia",
    "wof:placetype":"locality"
},
  "geometry": {"coordinates":[8.1123,33.91316],"type":"Point"}
}