{
  "type": "Feature",
  "properties": {
    "gn:admin1_code":"00",
    "gn:asciiname":"Beni Hazaz",
    "gn:cc2":"TN",
    "gn:country_code":"TN",
    "gn:dem":157,
    "gn:feature_class":"P",
    "gn:feature_code":"PPL",
    "gn:name":"Beni Hazaz",
    "gn:population":0,
    "gn:timezone":"Africa/Tunis",
    "iso:country":"TN",
    "name:und_x_variant":[
        "Ban\u012b Hazaz",
        "Beni Hazaxe",
        "Beni Hazaz"
    ],
    "wof:name":"Beni Hazaz",
    "wof:placetype":"locality"
},
  "geometry": {"coordinates":[10.89111,36.87306],"type":"Point"}
}