{
  "type": "Feature",
  "properties": {
    "gn:admin1_code":"18",
    "gn:asciiname":"Borj el Haj Salah",
    "gn:cc2":"TN",
    "gn:country_code":"TN",
    "gn:dem":130,
    "gn:feature_class":"P",
    "gn:feature_code":"PPL",
    "gn:name":"Borj el Haj Salah",
    "gn:population":0,
    "gn:timezone":"Africa/Tunis",
    "iso:country":"TN",
    "name:und_x_variant":[
        "Borj el Hadj Salah",
        "Borj el Haj Salah"
    ],
    "wof:name":"Borj el Haj Salah",
    "wof:placetype":"locality"
},
  "geometry": {"coordinates":[9.76222,37.09639],"type":"Point"}
}