{
  "type": "Feature",
  "properties": {
    "gn:admin1_code":"14",
    "gn:asciiname":"Seba Biar",
    "gn:cc2":"TN",
    "gn:country_code":"TN",
    "gn:dem":603,
    "gn:feature_class":"P",
    "gn:feature_code":"PPL",
    "gn:name":"Seba Biar",
    "gn:population":0,
    "gn:timezone":"Africa/Tunis",
    "iso:country":"TN",
    "name:und_x_variant":[
        "Sab\u2018 Bi\u2019\u0101r",
        "Seba Biar"
    ],
    "wof:name":"Seba Biar",
    "wof:placetype":"locality"
},
  "geometry": {"coordinates":[9.15389,35.99722],"type":"Point"}
}