{
  "type": "Feature",
  "properties": {
    "gn:admin1_code":"19",
    "gn:asciiname":"Douar Atmane Ben Hassene",
    "gn:cc2":"TN",
    "gn:country_code":"TN",
    "gn:dem":452,
    "gn:feature_class":"P",
    "gn:feature_code":"PPL",
    "gn:name":"Douar Atmane Ben Hassene",
    "gn:population":0,
    "gn:timezone":"Africa/Tunis",
    "iso:country":"TN",
    "name:und_x_variant":[
        "Douar Atmane Ben Hac\u00e9ne",
        "Daww\u0101r \u2018Uthm\u0101n Bin \u1e28asan",
        "Douar Atmane Ben Hassene"
    ],
    "wof:name":"Douar Atmane Ben Hassene",
    "wof:placetype":"locality"
},
  "geometry": {"coordinates":[10.4125,36.53556],"type":"Point"}
}