{
  "type": "Feature",
  "properties": {
    "gn:admin1_code":"32",
    "gn:asciiname":"Er-Remla",
    "gn:cc2":"TN",
    "gn:country_code":"TN",
    "gn:dem":2,
    "gn:feature_class":"P",
    "gn:feature_code":"PPL",
    "gn:name":"Er-Remla",
    "gn:population":0,
    "gn:timezone":"Africa/Tunis",
    "iso:country":"TN",
    "name:fra_x_preferred":[
        "Remla"
    ],
    "name:pol_x_preferred":[
        "Ar-Ramla"
    ],
    "name:ukr_x_preferred":[
        "\u0420\u0430\u043c\u043b\u0430"
    ],
    "name:und_x_variant":[
        "Ar Ramlah",
        "Ramla",
        "Er-Remla"
    ],
    "wof:lang_x_official":[
        "ara",
        "fra"
    ],
    "wof:lang_x_spoken":[
        "ara",
        "fra"
    ],
    "wof:name":"Er-Remla",
    "wof:placetype":"locality"
},
  "geometry": {"coordinates":[11.19444,34.71083],"type":"Point"}
}