{
  "type": "Feature",
  "properties": {
    "gn:admin1_code":"32",
    "gn:asciiname":"Er-Remla",
    "gn:cc2":"TN",
    "gn:country_code":"TN",
    "gn:dem":2,
    "gn:feature_class":"P",
    "gn:feature_code":"PPL",
    "gn:name":"Er-Remla",
    "gn:population":0,
    "gn:timezone":"Africa/Tunis",
    "iso:country":"TN",
    "name:und_x_variant":[
        "Ar Ramlah",
        "Ramla",
        "Remla",
        "Er-Remla"
    ],
    "wof:name":"Er-Remla",
    "wof:placetype":"locality"
},
  "geometry": {"coordinates":[11.19444,34.71083],"type":"Point"}
}