{
  "type": "Feature",
  "properties": {
    "gn:admin1_code":"34",
    "gn:asciiname":"Ksar Oulad Mahmed",
    "gn:country_code":"TN",
    "gn:dem":455,
    "gn:feature_class":"P",
    "gn:feature_code":"PPL",
    "gn:name":"Ksar Oulad Mahmed",
    "gn:population":0,
    "gn:timezone":"Africa/Tunis",
    "iso:country":"TN",
    "name:und_x_variant":[
        "Qa\u015fr Awl\u0101d Ma\u1e29mad"
    ],
    "wof:name":"Ksar Oulad Mahmed",
    "wof:placetype":"locality"
},
  "geometry": {"coordinates":[10.51667,32.88333],"type":"Point"}
}