{
  "type": "Feature",
  "properties": {
    "gn:admin1_code":"18",
    "gn:asciiname":"Douar Farouja",
    "gn:country_code":"TN",
    "gn:dem":34,
    "gn:feature_class":"P",
    "gn:feature_code":"PPL",
    "gn:name":"Douar Farouja",
    "gn:population":0,
    "gn:timezone":"Africa/Tunis",
    "iso:country":"TN",
    "name:und_x_variant":[
        "Daww\u0101r Farr\u016bjah",
        "Douar Faroudja",
        "Douar Farouja"
    ],
    "wof:name":"Douar Farouja",
    "wof:placetype":"locality"
},
  "geometry": {"coordinates":[9.64347,37.20593],"type":"Point"}
}