{
  "type": "Feature",
  "properties": {
    "gn:admin1_code":"29",
    "gn:asciiname":"El Maia",
    "gn:country_code":"TN",
    "gn:dem":28,
    "gn:feature_class":"P",
    "gn:feature_code":"PPL",
    "gn:name":"El Ma\u00efa",
    "gn:population":0,
    "gn:timezone":"Africa/Tunis",
    "iso:country":"TN",
    "name:und_x_variant":[
        "El Ma\u00efa",
        "Al M\u0101\u2019\u012byah"
    ],
    "wof:name":"El Maia",
    "wof:placetype":"locality"
},
  "geometry": {"coordinates":[10.01364,33.95797],"type":"Point"}
}