{
  "type": "Feature",
  "properties": {
    "gn:admin1_code":"00",
    "gn:asciiname":"Ez Zaouaouine",
    "gn:country_code":"TN",
    "gn:dem":12,
    "gn:feature_class":"P",
    "gn:feature_code":"PPL",
    "gn:name":"Ez Zaouaouine",
    "gn:population":0,
    "gn:timezone":"Africa/Tunis",
    "iso:country":"TN",
    "name:und_x_variant":[
        "Ez Zouaouine",
        "Az Zaw\u0101w\u012bn"
    ],
    "wof:name":"Ez Zaouaouine",
    "wof:placetype":"locality"
},
  "geometry": {"coordinates":[10.05734,37.12847],"type":"Point"}
}