{
  "type": "Feature",
  "properties": {
    "gn:country":"TN",
    "gn:fcode":"PPL",
    "gn:population":6442,
    "iso:country":"TN",
    "name:ara_x_preferred":[
        "\u0633\u0627\u0642\u064a\u0629 \u0633\u064a\u062f\u064a \u064a\u0648\u0633\u0641"
    ],
    "name:cat_x_preferred":[
        "Sakiet Sidi Youssef"
    ],
    "name:ceb_x_preferred":[
        "Sakiet Sidi Youssef"
    ],
    "name:deu_x_preferred":[
        "Sakiet Sidi Youssef"
    ],
    "name:eng_x_preferred":[
        "Sakiet Sidi Youssef"
    ],
    "name:fra_x_preferred":[
        "Sakiet Sidi Youssef"
    ],
    "name:nld_x_preferred":[
        "Sakiet Sidi Youssef"
    ],
    "name:rus_x_preferred":[
        "\u0421\u0430\u043a\u0435\u0442-\u0421\u0438\u0434\u0438-\u042e\u0441\u0435\u0444"
    ],
    "name:ukr_x_preferred":[
        "\u0421\u0430\u043a'\u0454\u0442-\u0421\u0456\u0434\u0456-\u042e\u0441\u0441\u0435\u0444"
    ],
    "name:und_x_variant":[
        "Sidi Youssef"
    ],
    "qs:name":"Sakiet Sidi Youssef",
    "qs:photos_9r":0,
    "qs:photos_sr":0,
    "qs:pop_sr":"5",
    "wd:wordcount":120,
    "wof:lang_x_official":[
        "ara",
        "fra"
    ],
    "wof:lang_x_spoken":[
        "ara",
        "fra"
    ],
    "wof:name":"Sakiet Sidi Youssef",
    "wof:placetype":"locality",
    "wof:population":6442
},
  "geometry": {"coordinates":[8.35547,36.22292],"type":"Point"}
}