{
  "type": "Feature",
  "properties": {
    "gn:admin1_code":"19",
    "gn:asciiname":"Douar Laheg Ben Merouah",
    "gn:country_code":"TN",
    "gn:dem":25,
    "gn:feature_class":"P",
    "gn:feature_code":"PPL",
    "gn:name":"Douar Laheg Ben Merouah",
    "gn:population":0,
    "gn:timezone":"Africa/Tunis",
    "iso:country":"TN",
    "wof:lang_x_official":[
        "ara",
        "fra"
    ],
    "wof:lang_x_spoken":[
        "ara",
        "fra"
    ],
    "wof:name":"Douar Laheg Ben Merouah",
    "wof:placetype":"locality"
},
  "geometry": {"coordinates":[10.96833,36.99417],"type":"Point"}
}