{
  "type": "Feature",
  "properties": {
    "gn:admin1_code":"18",
    "gn:asciiname":"El Bidha",
    "gn:country_code":"TN",
    "gn:dem":123,
    "gn:feature_class":"P",
    "gn:feature_code":"PPL",
    "gn:name":"El Bidha",
    "gn:population":0,
    "gn:timezone":"Africa/Tunis",
    "iso:country":"TN",
    "wof:lang_x_official":[
        "ara",
        "fra"
    ],
    "wof:lang_x_spoken":[
        "ara",
        "fra"
    ],
    "wof:name":"El Bidha",
    "wof:placetype":"locality"
},
  "geometry": {"coordinates":[9.2475,37.13917],"type":"Point"}
}