{
  "type": "Feature",
  "properties": {
    "gn:admin1_code":"32",
    "gn:asciiname":"Jedak Ali",
    "gn:cc2":"TN",
    "gn:country_code":"TN",
    "gn:dem":150,
    "gn:feature_class":"P",
    "gn:feature_code":"PPL",
    "gn:name":"Jedak Ali",
    "gn:population":0,
    "gn:timezone":"Africa/Tunis",
    "iso:country":"TN",
    "name:und_x_variant":[
        "Djedak Ali",
        "Jedak Ali"
    ],
    "wof:name":"Jedak Ali",
    "wof:placetype":"locality"
},
  "geometry": {"coordinates":[10.58972,34.97778],"type":"Point"}
}