{
  "type": "Feature",
  "properties": {
    "gn:admin1_code":"00",
    "gn:asciiname":"Douar Bed",
    "gn:country_code":"TN",
    "gn:dem":239,
    "gn:feature_class":"P",
    "gn:feature_code":"PPL",
    "gn:name":"Douar Bed",
    "gn:population":0,
    "gn:timezone":"Africa/Tunis",
    "iso:country":"TN",
    "name:und_x_variant":[
        "Le Bed",
        "Douar Bed",
        "Daww\u0101r Bed"
    ],
    "wof:name":"Douar Bed",
    "wof:placetype":"locality"
},
  "geometry": {"coordinates":[9.57849,36.79579],"type":"Point"}
}