{
  "type": "Feature",
  "properties": {
    "gn:admin1_code":"18",
    "gn:asciiname":"Douar Ben Sadek",
    "gn:country_code":"TN",
    "gn:dem":78,
    "gn:feature_class":"P",
    "gn:feature_code":"PPL",
    "gn:name":"Douar Ben Sadek",
    "gn:population":0,
    "gn:timezone":"Africa/Tunis",
    "iso:country":"TN",
    "wof:name":"Douar Ben Sadek",
    "wof:placetype":"locality"
},
  "geometry": {"coordinates":[9.96222,37.13861],"type":"Point"}
}