{
  "type": "Feature",
  "properties": {
    "gn:admin1_code":"00",
    "gn:asciiname":"Hennchir Goussa",
    "gn:country_code":"TN",
    "gn:dem":350,
    "gn:feature_class":"P",
    "gn:feature_code":"PPL",
    "gn:name":"Hennchir Goussa",
    "gn:population":0,
    "gn:timezone":"Africa/Tunis",
    "iso:country":"TN",
    "name:und_x_variant":[
        "Hansh\u012br al Qu\u015f\u015fah"
    ],
    "wof:lang_x_official":[
        "ara",
        "fra"
    ],
    "wof:lang_x_spoken":[
        "ara",
        "fra"
    ],
    "wof:name":"Hennchir Goussa",
    "wof:placetype":"locality"
},
  "geometry": {"coordinates":[9.03493,36.76918],"type":"Point"}
}