{
  "type": "Feature",
  "properties": {
    "gn:admin1_code":"00",
    "gn:asciiname":"Douala",
    "gn:country_code":"TN",
    "gn:dem":74,
    "gn:feature_class":"P",
    "gn:feature_code":"PPL",
    "gn:name":"Douala",
    "gn:population":0,
    "gn:timezone":"Africa/Tunis",
    "iso:country":"TN",
    "name:und_x_variant":[
        "Duela",
        "Douala",
        "Daw\u0101lah"
    ],
    "wof:name":"Douala",
    "wof:placetype":"locality"
},
  "geometry": {"coordinates":[10.61201,36.83159000000001],"type":"Point"}
}