{
  "type": "Feature",
  "properties": {
    "gn:admin1_code":"03",
    "gn:asciiname":"Ain Mestour",
    "gn:country_code":"TN",
    "gn:dem":416,
    "gn:feature_class":"P",
    "gn:feature_code":"PPL",
    "gn:name":"A\u00efn Mestour",
    "gn:population":0,
    "gn:timezone":"Africa/Tunis",
    "iso:country":"TN",
    "name:und_x_variant":[
        "\u2018Ayn Mast\u016br",
        "A\u00efn Mestour"
    ],
    "wof:name":"Ain Mestour",
    "wof:placetype":"locality"
},
  "geometry": {"coordinates":[9.62654,35.90176],"type":"Point"}
}