{
  "type": "Feature",
  "properties": {
    "gn:admin1_code":"23",
    "gn:asciiname":"Douar Hamama",
    "gn:country_code":"TN",
    "gn:dem":38,
    "gn:feature_class":"P",
    "gn:feature_code":"PPL",
    "gn:name":"Douar Hamama",
    "gn:population":0,
    "gn:timezone":"Africa/Tunis",
    "iso:country":"TN",
    "wof:name":"Douar Hamama",
    "wof:placetype":"locality"
},
  "geometry": {"coordinates":[10.26361,35.76],"type":"Point"}
}