{
  "type": "Feature",
  "properties": {
    "gn:admin1_code":"31",
    "gn:asciiname":"Ain Zigzaou",
    "gn:country_code":"TN",
    "gn:dem":110,
    "gn:feature_class":"P",
    "gn:feature_code":"PPL",
    "gn:name":"A\u00efn Zigzaou",
    "gn:population":0,
    "gn:timezone":"Africa/Tunis",
    "iso:country":"TN",
    "name:und_x_variant":[
        "A\u00efn Zigzaou",
        "A\u00efne Zigzaou",
        "\u2018Ayn Z\u012bqz\u0101w"
    ],
    "wof:name":"Ain Zigzaou",
    "wof:placetype":"locality"
},
  "geometry": {"coordinates":[9.21638,33.73454],"type":"Point"}
}