{
  "type": "Feature",
  "properties": {
    "gn:admin1_code":"06",
    "gn:asciiname":"Et Tahma",
    "gn:country_code":"TN",
    "gn:dem":200,
    "gn:feature_class":"P",
    "gn:feature_code":"PPL",
    "gn:name":"Et Tahma",
    "gn:population":0,
    "gn:timezone":"Africa/Tunis",
    "iso:country":"TN",
    "wof:name":"Et Tahma",
    "wof:placetype":"locality"
},
  "geometry": {"coordinates":[8.51755,36.51307],"type":"Point"}
}