{
  "type": "Feature",
  "properties": {
    "gn:admin1_code":"18",
    "gn:asciiname":"Douar et Tahouna",
    "gn:country_code":"TN",
    "gn:dem":16,
    "gn:feature_class":"P",
    "gn:feature_code":"PPL",
    "gn:name":"Douar et Tahouna",
    "gn:population":0,
    "gn:timezone":"Africa/Tunis",
    "iso:country":"TN",
    "wof:name":"Douar et Tahouna",
    "wof:placetype":"locality"
},
  "geometry": {"coordinates":[9.64869,37.0259],"type":"Point"}
}