{
  "type": "Feature",
  "properties": {
    "iso:country":"TN",
    "name:unk_x_variant":[
        "Redevef"
    ],
    "qs:gn_country":"TN",
    "qs:gn_fcode":"PPL",
    "qs:gn_pop":30048,
    "qs:name":"Ar Rudayyif",
    "qs:name_adm0":"Tunisia",
    "qs:name_adm1":"Qafash",
    "qs:photos":0,
    "qs:photos_1k":0,
    "qs:photos_9k":1,
    "qs:photos_9r":1,
    "qs:photos_all":11,
    "qs:photos_sr":0,
    "qs:placetype":"Town",
    "qs:pop_sr":"7",
    "qs:woe_adm0":23424967,
    "wof:name":"Ar Rudayyif",
    "wof:placetype":"locality",
    "wof:population":30048
},
  "geometry": {"coordinates":[8.15549,34.3827],"type":"Point"}
}