{
  "type": "Feature",
  "properties": {
    "gn:admin1_code":"18",
    "gn:asciiname":"Henchir el Merazguia",
    "gn:country_code":"TN",
    "gn:dem":29,
    "gn:feature_class":"P",
    "gn:feature_code":"PPL",
    "gn:name":"Henchir el Merazguia",
    "gn:population":0,
    "gn:timezone":"Africa/Tunis",
    "iso:country":"TN",
    "name:und_x_variant":[
        "Dar Merazguia",
        "Hansh\u012br al Mar\u0101ziq\u012byah",
        "Hennchir el Merazguia",
        "Henchir el Merazguia"
    ],
    "wof:name":"Henchir el Merazguia",
    "wof:placetype":"locality"
},
  "geometry": {"coordinates":[9.59712,37.19877],"type":"Point"}
}