{
  "type": "Feature",
  "properties": {
    "gn:admin1_code":"03",
    "gn:asciiname":"Cheikh Hamed",
    "gn:country_code":"TN",
    "gn:dem":97,
    "gn:feature_class":"P",
    "gn:feature_code":"PPL",
    "gn:name":"Cheikh Hamed",
    "gn:population":0,
    "gn:timezone":"Africa/Tunis",
    "iso:country":"TN",
    "wof:name":"Cheikh Hamed",
    "wof:placetype":"locality"
},
  "geometry": {"coordinates":[9.97672,35.96821],"type":"Point"}
}