{
  "type": "Feature",
  "properties": {
    "gn:admin1_code":"00",
    "gn:asciiname":"Dar Hassene el Mrabott",
    "gn:country_code":"TN",
    "gn:dem":399,
    "gn:feature_class":"P",
    "gn:feature_code":"PPL",
    "gn:name":"Dar Hassene el Mrabott",
    "gn:population":0,
    "gn:timezone":"Africa/Tunis",
    "iso:country":"TN",
    "name:und_x_variant":[
        "D\u0101r \u1e28asan al Mur\u0101bi\u0163"
    ],
    "wof:name":"Dar Hassene el Mrabott",
    "wof:placetype":"locality"
},
  "geometry": {"coordinates":[9.46667,36.96667],"type":"Point"}
}