{
  "type": "Feature",
  "properties": {
    "gn:admin1_code":"19",
    "gn:asciiname":"Dar Brahim Ben Assassa",
    "gn:country_code":"TN",
    "gn:dem":96,
    "gn:feature_class":"P",
    "gn:feature_code":"PPL",
    "gn:name":"Dar Brahim Ben Assassa",
    "gn:population":0,
    "gn:timezone":"Africa/Tunis",
    "iso:country":"TN",
    "wof:lang_x_official":[
        "ara",
        "fra"
    ],
    "wof:lang_x_spoken":[
        "ara",
        "fra"
    ],
    "wof:name":"Dar Brahim Ben Assassa",
    "wof:placetype":"locality"
},
  "geometry": {"coordinates":[10.83917,36.93306],"type":"Point"}
}