{
  "type": "Feature",
  "properties": {
    "gn:admin1_code":"06",
    "gn:asciiname":"En Merhamcha",
    "gn:country_code":"TN",
    "gn:dem":137,
    "gn:feature_class":"P",
    "gn:feature_code":"PPL",
    "gn:name":"En Merhamcha",
    "gn:population":0,
    "gn:timezone":"Africa/Tunis",
    "iso:country":"TN",
    "name:und_x_variant":[
        "An Nagh\u0101mishah",
        "En Nerhamcha",
        "En Merhamcha"
    ],
    "wof:lang_x_official":[
        "ara",
        "fra"
    ],
    "wof:lang_x_spoken":[
        "ara",
        "fra"
    ],
    "wof:name":"En Merhamcha",
    "wof:placetype":"locality"
},
  "geometry": {"coordinates":[8.7927,36.5338],"type":"Point"}
}