{
  "type": "Feature",
  "properties": {
    "gn:admin1_code":"00",
    "gn:asciiname":"Dar Hassine Ben Ameur",
    "gn:cc2":"TN",
    "gn:country_code":"TN",
    "gn:dem":74,
    "gn:feature_class":"P",
    "gn:feature_code":"PPL",
    "gn:name":"Dar Hassine Ben Ameur",
    "gn:population":0,
    "gn:timezone":"Africa/Tunis",
    "iso:country":"TN",
    "name:und_x_variant":[
        "D\u0101r \u1e28usayn Bin \u2018\u0100mir",
        "Dar Hessine Ben Amor",
        "Dar Hassine Ben Ameur"
    ],
    "wof:name":"Dar Hassine Ben Ameur",
    "wof:placetype":"locality"
},
  "geometry": {"coordinates":[10.85389,36.77972000000001],"type":"Point"}
}