{
  "type": "Feature",
  "properties": {
    "gn:admin1_code":"23",
    "gn:asciiname":"Beni Kaltoum",
    "gn:country_code":"TN",
    "gn:dem":52,
    "gn:feature_class":"P",
    "gn:feature_code":"PPL",
    "gn:name":"Beni Kaltoum",
    "gn:population":0,
    "gn:timezone":"Africa/Tunis",
    "iso:country":"TN",
    "name:und_x_variant":[
        "Beni Kraltun",
        "Beni Kaltoum",
        "Beni Khaltoun",
        "Beni Kraltoum",
        "Ban\u012b Kulth\u016bm"
    ],
    "wof:name":"Beni Kaltoum",
    "wof:placetype":"locality"
},
  "geometry": {"coordinates":[10.58901,35.7015],"type":"Point"}
}