{
  "type": "Feature",
  "properties": {
    "gn:admin1_code":"18",
    "gn:asciiname":"Dar ech Cheikh Amor Ben Ali",
    "gn:country_code":"TN",
    "gn:dem":294,
    "gn:feature_class":"P",
    "gn:feature_code":"PPL",
    "gn:name":"Dar ech Che\u00efkh Amor Ben Ali",
    "gn:population":0,
    "gn:timezone":"Africa/Tunis",
    "iso:country":"TN",
    "wof:name":"Dar ech Cheikh Amor Ben Ali",
    "wof:placetype":"locality"
},
  "geometry": {"coordinates":[9.39417,37.02639],"type":"Point"}
}