{
  "type": "Feature",
  "properties": {
    "gn:admin1_code":"00",
    "gn:asciiname":"Douar Zougjag",
    "gn:cc2":"TN",
    "gn:country_code":"TN",
    "gn:dem":56,
    "gn:feature_class":"P",
    "gn:feature_code":"PPL",
    "gn:name":"Douar Zougjag",
    "gn:population":0,
    "gn:timezone":"Africa/Tunis",
    "iso:country":"TN",
    "name:und_x_variant":[
        "Douar Zougdjag",
        "Douar Zougjag"
    ],
    "wof:name":"Douar Zougjag",
    "wof:placetype":"locality"
},
  "geometry": {"coordinates":[10.81111,36.90028],"type":"Point"}
}