{
  "type": "Feature",
  "properties": {
    "gn:admin1_code":"31",
    "gn:asciiname":"Oum es Somaa",
    "gn:country_code":"TN",
    "gn:dem":43,
    "gn:feature_class":"P",
    "gn:feature_code":"PPL",
    "gn:name":"Oum es Somaa",
    "gn:population":0,
    "gn:timezone":"Africa/Tunis",
    "iso:country":"TN",
    "name:und_x_variant":[
        "Umm a\u015f \u015eawma\u2018ah",
        "Oum Soumaa",
        "Oum Semaa",
        "Oum es Somaa"
    ],
    "wof:name":"Oum es Somaa",
    "wof:placetype":"locality"
},
  "geometry": {"coordinates":[8.81552,33.78518],"type":"Point"}
}