{
  "type": "Feature",
  "properties": {
    "gn:admin1_code":"28",
    "gn:asciiname":"Robbana",
    "gn:country_code":"TN",
    "gn:dem":25,
    "gn:feature_class":"P",
    "gn:feature_code":"PPL",
    "gn:name":"Robbana",
    "gn:population":0,
    "gn:timezone":"Africa/Tunis",
    "iso:country":"TN",
    "wof:name":"Robbana",
    "wof:placetype":"locality"
},
  "geometry": {"coordinates":[10.90111,33.76774],"type":"Point"}
}