{
  "type": "Feature",
  "properties": {
    "gn:admin1_code":"27",
    "gn:asciiname":"El Mourouj",
    "gn:country_code":"TN",
    "gn:dem":20,
    "gn:feature_class":"P",
    "gn:feature_code":"PPL",
    "gn:name":"El Mourouj",
    "gn:population":0,
    "gn:timezone":"Africa/Tunis",
    "iso:country":"TN",
    "wof:name":"El Mourouj",
    "wof:placetype":"locality"
},
  "geometry": {"coordinates":[10.2096,36.71364000000001],"type":"Point"}
}