{
  "type": "Feature",
  "properties": {
    "gn:admin1_code":"27",
    "gn:asciiname":"El Mourouj",
    "gn:country_code":"TN",
    "gn:dem":20,
    "gn:feature_class":"P",
    "gn:feature_code":"PPL",
    "gn:name":"El Mourouj",
    "gn:population":0,
    "gn:timezone":"Africa/Tunis",
    "iso:country":"TN",
    "name:ara_x_preferred":[
        "\u0627\u0644\u0645\u0631\u0648\u062c"
    ],
    "name:azb_x_preferred":[
        "\u0627\u0644\u0645\u0631\u0648\u062c"
    ],
    "name:cat_x_preferred":[
        "El Mourouj"
    ],
    "name:ell_x_preferred":[
        "\u0395\u03bb \u039c\u03bf\u03c5\u03c1\u03bf\u03cd\u03c4\u03b6"
    ],
    "name:fas_x_preferred":[
        "\u0627\u0644\u0645\u0631\u0648\u062c"
    ],
    "name:fra_x_preferred":[
        "El Mourouj"
    ],
    "name:ita_x_preferred":[
        "El Mourouj"
    ],
    "name:jpn_x_preferred":[
        "\u30a8\u30eb\u30fb\u30e2\u30a6\u30ed\u30a6\u30a3"
    ],
    "name:kat_x_preferred":[
        "\u10d4\u10da-\u10db\u10e3\u10e0\u10e3\u10ef\u10d8"
    ],
    "name:nld_x_preferred":[
        "El Mourouj"
    ],
    "name:sco_x_preferred":[
        "El Mourouj"
    ],
    "name:ukr_x_preferred":[
        "\u0415\u043b\u044c-\u041c\u0443\u0440\u0443\u0434\u0436"
    ],
    "name:urd_x_preferred":[
        "\u0627\u0644\u0645\u0631\u0648\u062c"
    ],
    "wof:name":"El Mourouj",
    "wof:placetype":"locality"
},
  "geometry": {"coordinates":[10.2096,36.71364000000001],"type":"Point"}
}