{
  "type": "Feature",
  "properties": {
    "gn:admin1_code":"23",
    "gn:asciiname":"Bou Rebia",
    "gn:country_code":"TN",
    "gn:dem":54,
    "gn:feature_class":"P",
    "gn:feature_code":"PPL",
    "gn:name":"Bou Rebia",
    "gn:population":0,
    "gn:timezone":"Africa/Tunis",
    "iso:country":"TN",
    "name:und_x_variant":[
        "B\u016b ar Rab\u012b\u2018ah"
    ],
    "wof:name":"Bou Rebia",
    "wof:placetype":"locality"
},
  "geometry": {"coordinates":[10.57314,35.67481],"type":"Point"}
}