{
  "type": "Feature",
  "properties": {
    "gn:admin1_code":"03",
    "gn:asciiname":"Sidi Mohammed Ben Mabrouk",
    "gn:cc2":"TN",
    "gn:country_code":"TN",
    "gn:dem":54,
    "gn:feature_class":"P",
    "gn:feature_code":"PPL",
    "gn:name":"Sidi Mohammed Ben Mabrouk",
    "gn:population":0,
    "gn:timezone":"Africa/Tunis",
    "iso:country":"TN",
    "name:und_x_variant":[
        "S\u012bd\u012b Mu\u1e29ammad Bin Mabr\u016bk",
        "Sidi Mohammed Ben Mabrouk"
    ],
    "wof:name":"Sidi Mohammed Ben Mabrouk",
    "wof:placetype":"locality"
},
  "geometry": {"coordinates":[10.17917,35.99805999999999],"type":"Point"}
}