{
  "type": "Feature",
  "properties": {
    "gn:admin1_code":"34",
    "gn:asciiname":"Ksar ech Chehbane",
    "gn:country_code":"TN",
    "gn:dem":241,
    "gn:feature_class":"P",
    "gn:feature_code":"PPL",
    "gn:name":"Ksar ech Chehbane",
    "gn:population":0,
    "gn:timezone":"Africa/Tunis",
    "iso:country":"TN",
    "name:und_x_variant":[
        "Qa\u015fr ash Shuhb\u0101n"
    ],
    "wof:name":"Ksar ech Chehbane",
    "wof:placetype":"locality"
},
  "geometry": {"coordinates":[10.38333,32.98333],"type":"Point"}
}