{
  "type": "Feature",
  "properties": {
    "gn:admin1_code":"33",
    "gn:asciiname":"Douar Souarigue",
    "gn:country_code":"TN",
    "gn:dem":390,
    "gn:feature_class":"P",
    "gn:feature_code":"PPL",
    "gn:name":"Douar Souarigue",
    "gn:population":0,
    "gn:timezone":"Africa/Tunis",
    "iso:country":"TN",
    "wof:name":"Douar Souarigue",
    "wof:placetype":"locality"
},
  "geometry": {"coordinates":[9.46917,35.30305999999999],"type":"Point"}
}