{
  "type": "Feature",
  "properties": {
    "gn:admin1_code":"00",
    "gn:asciiname":"Sidi Nadji",
    "gn:country_code":"TN",
    "gn:dem":115,
    "gn:feature_class":"P",
    "gn:feature_code":"PPL",
    "gn:name":"Sidi Nadji",
    "gn:population":0,
    "gn:timezone":"Africa/Tunis",
    "iso:country":"TN",
    "name:und_x_variant":[
        "Sidi Bou Nadji",
        "Sidi Nadji",
        "S\u012bd\u012b N\u0101j\u012b"
    ],
    "wof:name":"Sidi Nadji",
    "wof:placetype":"locality"
},
  "geometry": {"coordinates":[10.04901,36.05253],"type":"Point"}
}