{
  "type": "Feature",
  "properties": {
    "gn:admin1_code":"18",
    "gn:asciiname":"Douar Besbessia",
    "gn:country_code":"TN",
    "gn:dem":108,
    "gn:feature_class":"P",
    "gn:feature_code":"PPL",
    "gn:name":"Douar Besbessia",
    "gn:population":0,
    "gn:timezone":"Africa/Tunis",
    "iso:country":"TN",
    "wof:name":"Douar Besbessia",
    "wof:placetype":"locality"
},
  "geometry": {"coordinates":[9.9475,37.06306],"type":"Point"}
}