{
  "type": "Feature",
  "properties": {
    "gn:admin1_code":"03",
    "gn:asciiname":"Laouainiah",
    "gn:country_code":"TN",
    "gn:dem":273,
    "gn:feature_class":"P",
    "gn:feature_code":"PPL",
    "gn:name":"Laouainiah",
    "gn:population":0,
    "gn:timezone":"Africa/Tunis",
    "iso:country":"TN",
    "wof:name":"Laouainiah",
    "wof:placetype":"locality"
},
  "geometry": {"coordinates":[9.8525,35.17444],"type":"Point"}
}