{
  "type": "Feature",
  "properties": {
    "gn:admin1_code":"30",
    "gn:asciiname":"El Guetar",
    "gn:country_code":"TN",
    "gn:dem":241,
    "gn:feature_class":"P",
    "gn:feature_code":"PPL",
    "gn:name":"El Guetar",
    "gn:population":0,
    "gn:timezone":"Africa/Tunis",
    "iso:country":"TN",
    "name:ara_x_preferred":[
        "\u0627\u0644\u0642\u0637\u0627\u0631"
    ],
    "name:cat_x_preferred":[
        "Guetar"
    ],
    "name:deu_x_preferred":[
        "El Guettar"
    ],
    "name:fra_x_preferred":[
        "El Guettar"
    ],
    "name:ita_x_preferred":[
        "El Guettar"
    ],
    "name:ukr_x_preferred":[
        "\u0415\u043b\u044c-\u041a\u0430\u0442\u0430\u0440"
    ],
    "name:und_x_variant":[
        "Al Qa\u0163\u0163\u0101r",
        "El Guetar"
    ],
    "wof:name":"El Guetar",
    "wof:placetype":"locality"
},
  "geometry": {"coordinates":[8.94964,34.33628],"type":"Point"}
}