{
  "type": "Feature",
  "properties": {
    "gn:admin1_code":"14",
    "gn:asciiname":"Douar el Gouadria",
    "gn:country_code":"TN",
    "gn:dem":757,
    "gn:feature_class":"P",
    "gn:feature_code":"PPL",
    "gn:name":"Douar el Gouadria",
    "gn:population":0,
    "gn:timezone":"Africa/Tunis",
    "iso:country":"TN",
    "name:und_x_variant":[
        "Daww\u0101r al Qaw\u0101dir\u012byah"
    ],
    "wof:name":"Douar el Gouadria",
    "wof:placetype":"locality"
},
  "geometry": {"coordinates":[8.98333,35.75],"type":"Point"}
}