{
  "type": "Feature",
  "properties": {
    "gn:admin1_code":"32",
    "gn:asciiname":"Markez Bou Ladiab",
    "gn:country_code":"TN",
    "gn:dem":133,
    "gn:feature_class":"P",
    "gn:feature_code":"PPL",
    "gn:name":"Markez Bou Ladiab",
    "gn:population":0,
    "gn:timezone":"Africa/Tunis",
    "iso:country":"TN",
    "wof:lang_x_official":[
        "ara",
        "fra"
    ],
    "wof:lang_x_spoken":[
        "ara",
        "fra"
    ],
    "wof:name":"Markez Bou Ladiab",
    "wof:placetype":"locality"
},
  "geometry": {"coordinates":[10.37278,34.74222],"type":"Point"}
}