{
  "type": "Feature",
  "properties": {
    "iso:country":"TN",
    "name:und_x_variant":[
        "\u015eabr\u012byah"
    ],
    "qs:gn_country":"TN",
    "qs:gn_fcode":"PPL",
    "qs:gn_pop":0,
    "qs:name":"Sabriyah",
    "qs:name_adm0":"Tunisia",
    "qs:name_adm1":"Qibili",
    "qs:photos":131,
    "qs:photos_1k":27,
    "qs:photos_9k":1,
    "qs:photos_9r":3,
    "qs:photos_all":131,
    "qs:photos_sr":3,
    "qs:placetype":"Town",
    "qs:pop_sr":"3",
    "qs:woe_adm0":23424967,
    "wof:lang_x_official":[
        "ara",
        "fra"
    ],
    "wof:lang_x_spoken":[
        "ara",
        "fra"
    ],
    "wof:name":"Sabriyah",
    "wof:placetype":"locality"
},
  "geometry": {"coordinates":[8.74703,33.35699],"type":"Point"}
}