{
  "type": "Feature",
  "properties": {
    "gn:admin1_code":"00",
    "gn:asciiname":"Bou Djelida",
    "gn:country_code":"TN",
    "gn:dem":215,
    "gn:feature_class":"P",
    "gn:feature_code":"PPL",
    "gn:name":"Bou Djelida",
    "gn:population":0,
    "gn:timezone":"Africa/Tunis",
    "iso:country":"TN",
    "name:und_x_variant":[
        "Dachret Bou Djelida",
        "Dachret Bou Djehda",
        "B\u016b Jal\u012bdah"
    ],
    "wof:lang_x_official":[
        "ara",
        "fra"
    ],
    "wof:lang_x_spoken":[
        "ara",
        "fra"
    ],
    "wof:name":"Bou Djelida",
    "wof:placetype":"locality"
},
  "geometry": {"coordinates":[9.50493,36.41574],"type":"Point"}
}