{
  "type": "Feature",
  "properties": {
    "gn:admin1_code":"18",
    "gn:asciiname":"Douar er Roumane",
    "gn:country_code":"TN",
    "gn:dem":196,
    "gn:feature_class":"P",
    "gn:feature_code":"PPL",
    "gn:name":"Douar er Roumane",
    "gn:population":0,
    "gn:timezone":"Africa/Tunis",
    "iso:country":"TN",
    "wof:name":"Douar er Roumane",
    "wof:placetype":"locality"
},
  "geometry": {"coordinates":[9.95417,37.09806],"type":"Point"}
}