{
  "type": "Feature",
  "properties": {
    "gn:admin1_code":"18",
    "gn:asciiname":"Borj Ouichka",
    "gn:country_code":"TN",
    "gn:dem":26,
    "gn:feature_class":"P",
    "gn:feature_code":"PPL",
    "gn:name":"Borj Ouichka",
    "gn:population":0,
    "gn:timezone":"Africa/Tunis",
    "iso:country":"TN",
    "wof:name":"Borj Ouichka",
    "wof:placetype":"locality"
},
  "geometry": {"coordinates":[9.88944,37.03611],"type":"Point"}
}