{
  "type": "Feature",
  "properties": {
    "gn:admin1_code":"34",
    "gn:asciiname":"Ksar el Ababsa",
    "gn:country_code":"TN",
    "gn:dem":222,
    "gn:feature_class":"P",
    "gn:feature_code":"PPL",
    "gn:name":"Ksar el Ababsa",
    "gn:population":0,
    "gn:timezone":"Africa/Tunis",
    "iso:country":"TN",
    "name:und_x_variant":[
        "Qa\u015fr al \u2018Ab\u0101bisah"
    ],
    "wof:lang_x_official":[
        "ara",
        "fra"
    ],
    "wof:lang_x_spoken":[
        "ara",
        "fra"
    ],
    "wof:name":"Ksar el Ababsa",
    "wof:placetype":"locality"
},
  "geometry": {"coordinates":[10.38333,33.11667],"type":"Point"}
}