{
  "type": "Feature",
  "properties": {
    "gn:admin1_code":"18",
    "gn:asciiname":"Douar Amor Cherina",
    "gn:country_code":"TN",
    "gn:dem":153,
    "gn:feature_class":"P",
    "gn:feature_code":"PPL",
    "gn:name":"Douar Amor Cherina",
    "gn:population":0,
    "gn:timezone":"Africa/Tunis",
    "iso:country":"TN",
    "wof:name":"Douar Amor Cherina",
    "wof:placetype":"locality"
},
  "geometry": {"coordinates":[9.65944,37.24528],"type":"Point"}
}