{
  "type": "Feature",
  "properties": {
    "gn:admin1_code":"03",
    "gn:asciiname":"Et Trabelsia",
    "gn:cc2":"TN",
    "gn:country_code":"TN",
    "gn:dem":56,
    "gn:feature_class":"P",
    "gn:feature_code":"PPL",
    "gn:name":"Et Trabelsia",
    "gn:population":0,
    "gn:timezone":"Africa/Tunis",
    "iso:country":"TN",
    "name:und_x_variant":[
        "A\u0163 \u0162ar\u0101bulus\u012byah",
        "Et Trabelsia"
    ],
    "wof:lang_x_official":[
        "ara",
        "fra"
    ],
    "wof:lang_x_spoken":[
        "ara",
        "fra"
    ],
    "wof:name":"Et Trabelsia",
    "wof:placetype":"locality"
},
  "geometry": {"coordinates":[10.24944,35.96528],"type":"Point"}
}