{
  "type": "Feature",
  "properties": {
    "gn:admin1_code":"03",
    "gn:asciiname":"Dechret el Gamboura",
    "gn:cc2":"TN",
    "gn:country_code":"TN",
    "gn:dem":566,
    "gn:feature_class":"P",
    "gn:feature_code":"PPL",
    "gn:name":"Dechret el Gamboura",
    "gn:population":0,
    "gn:timezone":"Africa/Tunis",
    "iso:country":"TN",
    "name:und_x_variant":[
        "Dashrat al Qanb\u016brah",
        "Dechret el Gamboura"
    ],
    "wof:name":"Dechret el Gamboura",
    "wof:placetype":"locality"
},
  "geometry": {"coordinates":[9.5425,35.89528],"type":"Point"}
}