{
  "type": "Feature",
  "properties": {
    "gn:admin1_code":"32",
    "gn:asciiname":"Dar el Haj Mohammed Mallak",
    "gn:cc2":"TN",
    "gn:country_code":"TN",
    "gn:dem":7,
    "gn:feature_class":"P",
    "gn:feature_code":"PPL",
    "gn:name":"Dar el Haj Mohammed Mallak",
    "gn:population":0,
    "gn:timezone":"Africa/Tunis",
    "iso:country":"TN",
    "name:und_x_variant":[
        "Dar el Hadj Mohammed Mallak",
        "Dar el Haj Mohammed Mallak"
    ],
    "wof:name":"Dar el Haj Mohammed Mallak",
    "wof:placetype":"locality"
},
  "geometry": {"coordinates":[10.78361,34.78055999999999],"type":"Point"}
}