{
  "type": "Feature",
  "properties": {
    "gn:admin1_code":"18",
    "gn:asciiname":"Dar Mohammed Bel Haj",
    "gn:country_code":"TN",
    "gn:dem":203,
    "gn:feature_class":"P",
    "gn:feature_code":"PPL",
    "gn:name":"Dar Mohammed Bel Haj",
    "gn:population":0,
    "gn:timezone":"Africa/Tunis",
    "iso:country":"TN",
    "name:und_x_variant":[
        "Dar Mohammed Bel Hadj",
        "Dar Mohammed Bel Haj"
    ],
    "wof:name":"Dar Mohammed Bel Haj",
    "wof:placetype":"locality"
},
  "geometry": {"coordinates":[9.47222,37.05194],"type":"Point"}
}