{
  "type": "Feature",
  "properties": {
    "gn:admin1_code":"23",
    "gn:asciiname":"Ben Khirat",
    "gn:country_code":"TN",
    "gn:dem":18,
    "gn:feature_class":"P",
    "gn:feature_code":"PPL",
    "gn:name":"Ben Khirat",
    "gn:population":0,
    "gn:timezone":"Africa/Tunis",
    "iso:country":"TN",
    "wof:lang_x_official":[
        "ara",
        "fra"
    ],
    "wof:lang_x_spoken":[
        "ara",
        "fra"
    ],
    "wof:name":"Ben Khirat",
    "wof:placetype":"locality"
},
  "geometry": {"coordinates":[10.35333,36.00806],"type":"Point"}
}