{
  "type": "Feature",
  "properties": {
    "gn:admin1_code":"23",
    "gn:asciiname":"Souani el Adari",
    "gn:cc2":"TN",
    "gn:country_code":"TN",
    "gn:dem":17,
    "gn:feature_class":"P",
    "gn:feature_code":"PPL",
    "gn:name":"Souani el Adari",
    "gn:population":0,
    "gn:timezone":"Africa/Tunis",
    "iso:country":"TN",
    "name:und_x_variant":[
        "Saw\u0101n\u012b al \u2018Adh\u0101r\u012b",
        "Souani el Adari"
    ],
    "wof:name":"Souani el Adari",
    "wof:placetype":"locality"
},
  "geometry": {"coordinates":[10.56028,35.92055999999999],"type":"Point"}
}