{
  "type": "Feature",
  "properties": {
    "gn:admin1_code":"00",
    "gn:asciiname":"Dar Bou Guetaia",
    "gn:country_code":"TN",
    "gn:dem":337,
    "gn:feature_class":"P",
    "gn:feature_code":"PPL",
    "gn:name":"Dar Bou Guetaia",
    "gn:population":0,
    "gn:timezone":"Africa/Tunis",
    "iso:country":"TN",
    "name:und_x_variant":[
        "D\u0101r B\u016b Qa\u0163\u0163\u0101yah"
    ],
    "wof:name":"Dar Bou Guetaia",
    "wof:placetype":"locality"
},
  "geometry": {"coordinates":[9.00301,36.27187],"type":"Point"}
}