{
  "type": "Feature",
  "properties": {
    "gn:admin1_code":"27",
    "gn:asciiname":"Douar el Haj Jemaa",
    "gn:cc2":"TN",
    "gn:country_code":"TN",
    "gn:dem":89,
    "gn:feature_class":"P",
    "gn:feature_code":"PPL",
    "gn:name":"Douar el Haj Jemaa",
    "gn:population":0,
    "gn:timezone":"Africa/Tunis",
    "iso:country":"TN",
    "name:und_x_variant":[
        "Douar el Hadj Djemaa",
        "Douar el Haj Jemaa"
    ],
    "wof:lang_x_official":[
        "ara",
        "fra"
    ],
    "wof:lang_x_spoken":[
        "ara",
        "fra"
    ],
    "wof:name":"Douar el Haj Jemaa",
    "wof:placetype":"locality"
},
  "geometry": {"coordinates":[10.27222,36.59972],"type":"Point"}
}