{
  "type": "Feature",
  "properties": {
    "gn:admin1_code":"22",
    "gn:asciiname":"Dechret ez Zriba",
    "gn:cc2":"TN",
    "gn:country_code":"TN",
    "gn:dem":785,
    "gn:feature_class":"P",
    "gn:feature_code":"PPL",
    "gn:name":"Dechret ez Zriba",
    "gn:population":0,
    "gn:timezone":"Africa/Tunis",
    "iso:country":"TN",
    "name:und_x_variant":[
        "Dashrat az Zar\u012bbah",
        "Dechret ez Zriba"
    ],
    "wof:name":"Dechret ez Zriba",
    "wof:placetype":"locality"
},
  "geometry": {"coordinates":[9.51306,35.93360999999999],"type":"Point"}
}