{
  "type": "Feature",
  "properties": {
    "iso:country":"TN",
    "name:ara_x_preferred":[
        "\u0627\u0644\u0645\u062d\u0631\u0633"
    ],
    "name:bul_x_preferred":[
        "\u041c\u0430\u0445\u0438\u0440\u0435\u0441"
    ],
    "name:cat_x_preferred":[
        "Mahres"
    ],
    "name:ceb_x_preferred":[
        "Mahires"
    ],
    "name:cym_x_preferred":[
        "Mahr\u00e8s"
    ],
    "name:deu_x_preferred":[
        "Mahres"
    ],
    "name:eng_x_preferred":[
        "Mahares"
    ],
    "name:eng_x_variant":[
        "Mahres"
    ],
    "name:fas_x_preferred":[
        "\u0627\u0644\u0645\u062d\u0631\u0633"
    ],
    "name:fra_x_preferred":[
        "Mahr\u00e8s"
    ],
    "name:ita_x_preferred":[
        "Mahres"
    ],
    "name:mlt_x_preferred":[
        "Ma\u0127res"
    ],
    "name:nld_x_preferred":[
        "Mahares"
    ],
    "name:rus_x_preferred":[
        "\u041c\u0430\u0445\u0430\u0440\u0435\u0441"
    ],
    "name:tur_x_preferred":[
        "Mahris"
    ],
    "name:ukr_x_preferred":[
        "\u041c\u0430\u0445\u0440\u0435\u0441"
    ],
    "name:und_x_variant":[
        "Al Ma\u1e29ras"
    ],
    "name:zho_x_preferred":[
        "\u9a6c\u54c8\u96f7\u65af"
    ],
    "name:zul_x_preferred":[
        "Mahres"
    ],
    "qs:gn_country":"TN",
    "qs:gn_fcode":"PPL",
    "qs:gn_pop":0,
    "qs:name":"Al Mahras",
    "qs:name_adm0":"Tunisia",
    "qs:name_adm1":"Safaqis",
    "qs:photos":23,
    "qs:photos_1k":5,
    "qs:photos_9k":1,
    "qs:photos_9r":1,
    "qs:photos_all":23,
    "qs:photos_sr":1,
    "qs:placetype":"Town",
    "qs:pop_sr":"7",
    "qs:woe_adm0":23424967,
    "wof:name":"Al Mahras",
    "wof:placetype":"locality"
},
  "geometry": {"coordinates":[10.50083,34.5275],"type":"Point"}
}