{
  "type": "Feature",
  "properties": {
    "gn:admin1_code":"32",
    "gn:asciiname":"Borj el Haj Braik",
    "gn:country_code":"TN",
    "gn:dem":8,
    "gn:feature_class":"P",
    "gn:feature_code":"PPL",
    "gn:name":"Borj el Haj Bra\u00efk",
    "gn:population":0,
    "gn:timezone":"Africa/Tunis",
    "iso:country":"TN",
    "name:und_x_variant":[
        "Bordj el Hadj Bra\u00efk",
        "Borj el Haj Bra\u00efk"
    ],
    "wof:name":"Borj el Haj Braik",
    "wof:placetype":"locality"
},
  "geometry": {"coordinates":[10.88141,34.9047],"type":"Point"}
}