{
  "type": "Feature",
  "properties": {
    "gn:admin1_code":"15",
    "gn:asciiname":"Rejiche",
    "gn:country_code":"TN",
    "gn:dem":6,
    "gn:feature_class":"P",
    "gn:feature_code":"PPL",
    "gn:name":"Rejiche",
    "gn:population":0,
    "gn:timezone":"Africa/Tunis",
    "iso:country":"TN",
    "name:ara_x_preferred":[
        "\u0631\u062c\u064a\u0634"
    ],
    "name:ceb_x_preferred":[
        "Rejiche"
    ],
    "name:fra_x_preferred":[
        "Rejiche"
    ],
    "name:ron_x_preferred":[
        "Rejich"
    ],
    "name:ukr_x_preferred":[
        "\u0420\u0435\u0436\u0456\u0448"
    ],
    "name:und_x_variant":[
        "Ar Raj\u012bsh",
        "Raj\u012bsh",
        "Redjiche",
        "Rejish"
    ],
    "wof:name":"Rejiche",
    "wof:placetype":"locality"
},
  "geometry": {"coordinates":[11.03848,35.46665],"type":"Point"}
}