{
  "type": "Feature",
  "properties": {
    "gn:admin1_code":"15",
    "gn:asciiname":"Rejiche",
    "gn:country_code":"TN",
    "gn:dem":6,
    "gn:feature_class":"P",
    "gn:feature_code":"PPL",
    "gn:name":"Rejiche",
    "gn:population":0,
    "gn:timezone":"Africa/Tunis",
    "iso:country":"TN",
    "name:und_x_variant":[
        "Ar Raj\u012bsh",
        "Raj\u012bsh",
        "Redjiche",
        "Rejish",
        "Rejiche"
    ],
    "wof:name":"Rejiche",
    "wof:placetype":"locality"
},
  "geometry": {"coordinates":[11.03848,35.46665],"type":"Point"}
}