{
  "type": "Feature",
  "properties": {
    "gn:admin1_code":"34",
    "gn:asciiname":"Kasba Bou Nemcha",
    "gn:country_code":"TN",
    "gn:dem":180,
    "gn:feature_class":"P",
    "gn:feature_code":"PPL",
    "gn:name":"Kasba Bou Nemcha",
    "gn:population":0,
    "gn:timezone":"Africa/Tunis",
    "iso:country":"TN",
    "name:und_x_variant":[
        "Qa\u015fabat B\u016b Nemcha"
    ],
    "wof:lang_x_official":[
        "ara",
        "fra"
    ],
    "wof:lang_x_spoken":[
        "ara",
        "fra"
    ],
    "wof:name":"Kasba Bou Nemcha",
    "wof:placetype":"locality"
},
  "geometry": {"coordinates":[10.65,32.88333],"type":"Point"}
}