{
  "type": "Feature",
  "properties": {
    "gn:admin1_code":"19",
    "gn:asciiname":"Dar Oulad Daoued",
    "gn:country_code":"TN",
    "gn:dem":95,
    "gn:feature_class":"P",
    "gn:feature_code":"PPL",
    "gn:name":"Dar Oulad Daoued",
    "gn:population":0,
    "gn:timezone":"Africa/Tunis",
    "iso:country":"TN",
    "wof:name":"Dar Oulad Daoued",
    "wof:placetype":"locality"
},
  "geometry": {"coordinates":[10.85102,36.78898],"type":"Point"}
}