{
  "type": "Feature",
  "properties": {
    "gn:admin1_code":"18",
    "gn:asciiname":"Douar el Hofer",
    "gn:cc2":"TN",
    "gn:country_code":"TN",
    "gn:dem":286,
    "gn:feature_class":"P",
    "gn:feature_code":"PPL",
    "gn:name":"Douar el Hofer",
    "gn:population":0,
    "gn:timezone":"Africa/Tunis",
    "iso:country":"TN",
    "name:und_x_variant":[
        "Daww\u0101r al Hofer",
        "Douar el Hafer",
        "Douar el Hofer"
    ],
    "wof:lang_x_official":[
        "ara",
        "fra"
    ],
    "wof:lang_x_spoken":[
        "ara",
        "fra"
    ],
    "wof:name":"Douar el Hofer",
    "wof:placetype":"locality"
},
  "geometry": {"coordinates":[9.97056,37.11417],"type":"Point"}
}