{
  "type": "Feature",
  "properties": {
    "gn:admin1_code":"17",
    "gn:asciiname":"Gassa",
    "gn:country_code":"TN",
    "gn:dem":135,
    "gn:feature_class":"P",
    "gn:feature_code":"PPL",
    "gn:name":"Gassa",
    "gn:population":0,
    "gn:timezone":"Africa/Tunis",
    "iso:country":"TN",
    "wof:name":"Gassa",
    "wof:placetype":"locality"
},
  "geometry": {"coordinates":[9.01639,37.11917],"type":"Point"}
}