{
  "type": "Feature",
  "properties": {
    "gn:admin1_code":"29",
    "gn:asciiname":"Haddedj",
    "gn:country_code":"TN",
    "gn:dem":237,
    "gn:feature_class":"P",
    "gn:feature_code":"PPL",
    "gn:name":"Haddedj",
    "gn:population":0,
    "gn:timezone":"Africa/Tunis",
    "iso:country":"TN",
    "name:und_x_variant":[
        "Had\u00e8ge",
        "Haddej",
        "Hachache-Matmata",
        "Haddedj"
    ],
    "wof:name":"Haddedj",
    "wof:placetype":"locality"
},
  "geometry": {"coordinates":[9.99472,33.56865999999999],"type":"Point"}
}