{
  "type": "Feature",
  "properties": {
    "gn:admin1_code":"36",
    "gn:asciiname":"Borj Ali Ben Ammar",
    "gn:cc2":"TN",
    "gn:country_code":"TN",
    "gn:dem":8,
    "gn:feature_class":"P",
    "gn:feature_code":"PPL",
    "gn:name":"Borj Ali Ben Ammar",
    "gn:population":0,
    "gn:timezone":"Africa/Tunis",
    "iso:country":"TN",
    "name:und_x_variant":[
        "Bordj Ali Ben Ammar",
        "Burj \u2018Al\u012b Bin \u2018Amm\u0101r",
        "Borj Ali Ben Ahmar",
        "Bordj Ali Bene Ammar",
        "Bordj Adj Ali",
        "Borj Ali Ben Ammar"
    ],
    "wof:name":"Borj Ali Ben Ammar",
    "wof:placetype":"locality"
},
  "geometry": {"coordinates":[10.09278,37.00028],"type":"Point"}
}