{
  "type": "Feature",
  "properties": {
    "gn:admin1_code":"02",
    "gn:asciiname":"Ad Dulab",
    "gn:country_code":"TN",
    "gn:dem":931,
    "gn:feature_class":"P",
    "gn:feature_code":"PPL",
    "gn:name":"Ad D\u016bl\u0101b",
    "gn:population":0,
    "gn:timezone":"Africa/Tunis",
    "iso:country":"TN",
    "wof:name":"Ad Dulab",
    "wof:placetype":"locality"
},
  "geometry": {"coordinates":[8.8529,35.36322],"type":"Point"}
}