{
  "type": "Feature",
  "properties": {
    "gn:admin1_code":"00",
    "gn:asciiname":"Zaouia",
    "gn:country_code":"TN",
    "gn:dem":301,
    "gn:feature_class":"P",
    "gn:feature_code":"PPL",
    "gn:name":"Zaouia",
    "gn:population":0,
    "gn:timezone":"Africa/Tunis",
    "iso:country":"TN",
    "wof:name":"Zaouia",
    "wof:placetype":"locality"
},
  "geometry": {"coordinates":[8.97694,36.42667],"type":"Point"}
}