{
  "type": "Feature",
  "properties": {
    "gn:admin1_code":"18",
    "gn:asciiname":"Douar Haj Salah",
    "gn:cc2":"TN",
    "gn:country_code":"TN",
    "gn:dem":80,
    "gn:feature_class":"P",
    "gn:feature_code":"PPL",
    "gn:name":"Douar Haj Salah",
    "gn:population":0,
    "gn:timezone":"Africa/Tunis",
    "iso:country":"TN",
    "name:und_x_variant":[
        "Douar Hadj Salah",
        "Douar Haj Salah"
    ],
    "wof:lang_x_official":[
        "ara",
        "fra"
    ],
    "wof:lang_x_spoken":[
        "ara",
        "fra"
    ],
    "wof:name":"Douar Haj Salah",
    "wof:placetype":"locality"
},
  "geometry": {"coordinates":[9.92639,37.04361],"type":"Point"}
}