{
  "type": "Feature",
  "properties": {
    "gn:admin1_code":"28",
    "gn:asciiname":"Hassi Soltane",
    "gn:country_code":"TN",
    "gn:dem":50,
    "gn:feature_class":"P",
    "gn:feature_code":"PPL",
    "gn:name":"Hassi Soltane",
    "gn:population":0,
    "gn:timezone":"Africa/Tunis",
    "iso:country":"TN",
    "wof:name":"Hassi Soltane",
    "wof:placetype":"locality"
},
  "geometry": {"coordinates":[10.77784,33.32416],"type":"Point"}
}