{
  "type": "Feature",
  "properties": {
    "gn:admin1_code":"18",
    "gn:asciiname":"Douar el Hajerine",
    "gn:cc2":"TN",
    "gn:country_code":"TN",
    "gn:dem":9,
    "gn:feature_class":"P",
    "gn:feature_code":"PPL",
    "gn:name":"Douar el Hajerine",
    "gn:population":0,
    "gn:timezone":"Africa/Tunis",
    "iso:country":"TN",
    "name:und_x_variant":[
        "Douar el Hadjerine",
        "Daww\u0101r al Hadjerine",
        "El Hadjerine",
        "Douar el Hajerine"
    ],
    "wof:name":"Douar el Hajerine",
    "wof:placetype":"locality"
},
  "geometry": {"coordinates":[10.01639,36.95861],"type":"Point"}
}