{
  "type": "Feature",
  "properties": {
    "gn:admin1_code":"00",
    "gn:asciiname":"Sidi Amor Bou Zitouna",
    "gn:country_code":"TN",
    "gn:dem":403,
    "gn:feature_class":"P",
    "gn:feature_code":"PPL",
    "gn:name":"Sidi Amor Bou Zitouna",
    "gn:population":0,
    "gn:timezone":"Africa/Tunis",
    "iso:country":"TN",
    "name:und_x_variant":[
        "S\u012bd\u012b \u2018Umar B\u016b Zayt\u016bnah"
    ],
    "wof:lang_x_official":[
        "ara",
        "fra"
    ],
    "wof:lang_x_spoken":[
        "ara",
        "fra"
    ],
    "wof:name":"Sidi Amor Bou Zitouna",
    "wof:placetype":"locality"
},
  "geometry": {"coordinates":[9.36667,36.95],"type":"Point"}
}