{
  "type": "Feature",
  "properties": {
    "iso:country":"TN",
    "qs:gn_pop":0,
    "qs:name":"Al Muhammadiyah",
    "qs:name_adm0":"Tunisia",
    "qs:name_adm1":"Aryanah",
    "qs:photos":27,
    "qs:photos_1k":5,
    "qs:photos_9k":1,
    "qs:photos_9r":2,
    "qs:photos_all":27,
    "qs:photos_sr":2,
    "qs:placetype":"Town",
    "qs:pop_sr":"0",
    "qs:woe_adm0":23424967,
    "wof:name":"Al Muhammadiyah",
    "wof:placetype":"locality"
},
  "geometry": {"coordinates":[10.15274,36.64363],"type":"Point"}
}