{
  "type": "Feature",
  "properties": {
    "gn:admin1_code":"18",
    "gn:asciiname":"Douar Bechouk",
    "gn:country_code":"TN",
    "gn:dem":9,
    "gn:feature_class":"P",
    "gn:feature_code":"PPL",
    "gn:name":"Douar Bechouk",
    "gn:population":0,
    "gn:timezone":"Africa/Tunis",
    "iso:country":"TN",
    "name:und_x_variant":[
        "Daww\u0101r Bechouk",
        "Douar Bechouk"
    ],
    "wof:name":"Douar Bechouk",
    "wof:placetype":"locality"
},
  "geometry": {"coordinates":[9.58191,37.09862],"type":"Point"}
}