{
  "type": "Feature",
  "properties": {
    "gn:admin1_code":"00",
    "gn:asciiname":"Dashrat Chetlou",
    "gn:cc2":"TN",
    "gn:country_code":"TN",
    "gn:dem":536,
    "gn:feature_class":"P",
    "gn:feature_code":"PPL",
    "gn:name":"Dashrat Chetlou",
    "gn:population":0,
    "gn:timezone":"Africa/Tunis",
    "iso:country":"TN",
    "name:und_x_variant":[
        "Dechret Chetlou",
        "Dashrat Chetlou"
    ],
    "wof:name":"Dashrat Chetlou",
    "wof:placetype":"locality"
},
  "geometry": {"coordinates":[9.37945,36.42349],"type":"Point"}
}