{
  "type": "Feature",
  "properties": {
    "gn:admin1_code":"03",
    "gn:asciiname":"Dar Ahmed Mohammed Largueb",
    "gn:country_code":"TN",
    "gn:dem":358,
    "gn:feature_class":"P",
    "gn:feature_code":"PPL",
    "gn:name":"Dar Ahmed Mohammed Largueb",
    "gn:population":0,
    "gn:timezone":"Africa/Tunis",
    "iso:country":"TN",
    "wof:name":"Dar Ahmed Mohammed Largueb",
    "wof:placetype":"locality"
},
  "geometry": {"coordinates":[9.64556,35.26694000000001],"type":"Point"}
}