{
  "type": "Feature",
  "properties": {
    "gn:admin1_code":"36",
    "gn:asciiname":"Bab Sidi Kassem",
    "gn:country_code":"TN",
    "gn:dem":19,
    "gn:feature_class":"P",
    "gn:feature_code":"PPL",
    "gn:name":"Bab Sidi Kassem",
    "gn:population":0,
    "gn:timezone":"Africa/Tunis",
    "iso:country":"TN",
    "wof:name":"Bab Sidi Kassem",
    "wof:placetype":"locality"
},
  "geometry": {"coordinates":[10.16111,36.79361],"type":"Point"}
}