{
  "type": "Feature",
  "properties": {
    "gn:admin1_code":"31",
    "gn:asciiname":"Ain Radouane",
    "gn:country_code":"TN",
    "gn:dem":116,
    "gn:feature_class":"P",
    "gn:feature_code":"PPL",
    "gn:name":"A\u00efn Radouane",
    "gn:population":0,
    "gn:timezone":"Africa/Tunis",
    "iso:country":"TN",
    "name:und_x_variant":[
        "A\u00efne Radouane",
        "A\u00efn Radouane",
        "\u2018Ayn Ri\u1e11w\u0101n"
    ],
    "wof:lang_x_official":[
        "ara",
        "fra"
    ],
    "wof:lang_x_spoken":[
        "ara",
        "fra"
    ],
    "wof:name":"Ain Radouane",
    "wof:placetype":"locality"
},
  "geometry": {"coordinates":[9.23741,33.73323],"type":"Point"}
}