{
  "type": "Feature",
  "properties": {
    "gn:admin1_code":"17",
    "gn:asciiname":"Montarnaud",
    "gn:country_code":"TN",
    "gn:dem":115,
    "gn:feature_class":"P",
    "gn:feature_code":"PPL",
    "gn:name":"Montarnaud",
    "gn:population":0,
    "gn:timezone":"Africa/Tunis",
    "iso:country":"TN",
    "name:cat_x_preferred":[
        "Montarnaud"
    ],
    "name:ceb_x_preferred":[
        "Montarnaud"
    ],
    "name:deu_x_preferred":[
        "Montarnaud"
    ],
    "name:eus_x_preferred":[
        "Montarnaud"
    ],
    "name:fra_x_preferred":[
        "Montarnaud"
    ],
    "name:hun_x_preferred":[
        "Montarnaud"
    ],
    "name:ita_x_preferred":[
        "Montarnaud"
    ],
    "name:kaz_x_preferred":[
        "\u041c\u043e\u043d\u0442\u0430\u0440\u043d\u043e"
    ],
    "name:lat_x_preferred":[
        "Montarnaud"
    ],
    "name:lmo_x_preferred":[
        "Montarnaud"
    ],
    "name:mlg_x_preferred":[
        "Montarnaud"
    ],
    "name:msa_x_preferred":[
        "Montarnaud"
    ],
    "name:nld_x_preferred":[
        "Montarnaud"
    ],
    "name:oci_x_preferred":[
        "Montarnaud"
    ],
    "name:pms_x_preferred":[
        "Montarnaud"
    ],
    "name:pol_x_preferred":[
        "Montarnaud"
    ],
    "name:por_x_preferred":[
        "Montarnaud"
    ],
    "name:ron_x_preferred":[
        "Montarnaud"
    ],
    "name:slk_x_preferred":[
        "Montarnaud"
    ],
    "name:spa_x_preferred":[
        "Montarnaud"
    ],
    "name:swe_x_preferred":[
        "Montarnaud"
    ],
    "name:ukr_x_preferred":[
        "\u041c\u043e\u043d\u0442\u0430\u0440\u043d\u043e"
    ],
    "name:und_x_variant":[
        "Montarn"
    ],
    "name:vie_x_preferred":[
        "Montarnaud"
    ],
    "name:vol_x_preferred":[
        "Montarnaud"
    ],
    "name:war_x_preferred":[
        "Montarnaud"
    ],
    "name:zho_x_preferred":[
        "\u8499\u5854\u5c14\u8bfa"
    ],
    "wof:lang_x_official":[
        "ara",
        "fra"
    ],
    "wof:lang_x_spoken":[
        "ara",
        "fra"
    ],
    "wof:name":"Montarnaud",
    "wof:placetype":"locality"
},
  "geometry": {"coordinates":[9.75682,36.68319],"type":"Point"}
}