{
  "type": "Feature",
  "properties": {
    "gn:admin1_code":"17",
    "gn:asciiname":"Montarnaud",
    "gn:country_code":"TN",
    "gn:dem":115,
    "gn:feature_class":"P",
    "gn:feature_code":"PPL",
    "gn:name":"Montarnaud",
    "gn:population":0,
    "gn:timezone":"Africa/Tunis",
    "iso:country":"TN",
    "name:und_x_variant":[
        "Montarn",
        "Montarnaud"
    ],
    "wof:name":"Montarnaud",
    "wof:placetype":"locality"
},
  "geometry": {"coordinates":[9.75682,36.68319],"type":"Point"}
}