{
  "type": "Feature",
  "properties": {
    "gn:admin1_code":"03",
    "gn:asciiname":"Dar Ali Bey",
    "gn:country_code":"TN",
    "gn:dem":74,
    "gn:feature_class":"P",
    "gn:feature_code":"PPL",
    "gn:name":"Dar Ali Bey",
    "gn:population":0,
    "gn:timezone":"Africa/Tunis",
    "iso:country":"TN",
    "wof:name":"Dar Ali Bey",
    "wof:placetype":"locality"
},
  "geometry": {"coordinates":[9.90765,35.68308],"type":"Point"}
}