{
  "type": "Feature",
  "properties": {
    "gn:admin1_code":"14",
    "gn:asciiname":"Les Zouarines",
    "gn:country_code":"TN",
    "gn:dem":606,
    "gn:feature_class":"P",
    "gn:feature_code":"PPL",
    "gn:name":"Les Zouarines",
    "gn:population":0,
    "gn:timezone":"Africa/Tunis",
    "iso:country":"TN",
    "name:und_x_variant":[
        "Az Zuw\u0101r\u012bn"
    ],
    "wof:name":"Les Zouarines",
    "wof:placetype":"locality"
},
  "geometry": {"coordinates":[8.91667,36.01667],"type":"Point"}
}