{
  "type": "Feature",
  "properties": {
    "gn:admin1_code":"00",
    "gn:asciiname":"Tazarka",
    "gn:country_code":"TN",
    "gn:dem":13,
    "gn:feature_class":"P",
    "gn:feature_code":"PPL",
    "gn:name":"Tazarka",
    "gn:population":0,
    "gn:timezone":"Africa/Tunis",
    "iso:country":"TN",
    "name:ara_x_preferred":[
        "\u062a\u0627\u0632\u0631\u0643\u0629"
    ],
    "name:azb_x_preferred":[
        "\u062a\u0627\u0632\u0631\u06a9\u0647"
    ],
    "name:ceb_x_preferred":[
        "Tazarka"
    ],
    "name:fas_x_preferred":[
        "\u062a\u0627\u0632\u0631\u06a9\u0647"
    ],
    "name:fra_x_preferred":[
        "Tazarka"
    ],
    "name:ukr_x_preferred":[
        "\u0422\u0430\u0437\u0435\u0440\u043a\u0430"
    ],
    "name:und_x_variant":[
        "T\u0101zirkah",
        "Tazerka"
    ],
    "wof:lang_x_official":[
        "ara",
        "fra"
    ],
    "wof:lang_x_spoken":[
        "ara",
        "fra"
    ],
    "wof:name":"Tazarka",
    "wof:placetype":"locality"
},
  "geometry": {"coordinates":[10.83868,36.55367],"type":"Point"}
}