{
  "type": "Feature",
  "properties": {
    "gn:admin1_code":"00",
    "gn:asciiname":"Azib el Mroug",
    "gn:cc2":"TN",
    "gn:country_code":"TN",
    "gn:dem":795,
    "gn:feature_class":"P",
    "gn:feature_code":"PPL",
    "gn:name":"Azib el Mroug",
    "gn:population":0,
    "gn:timezone":"Africa/Tunis",
    "iso:country":"TN",
    "name:und_x_variant":[
        "\u2018Az\u012bb al Mur\u016bq",
        "Azib el Mroug"
    ],
    "wof:name":"Azib el Mroug",
    "wof:placetype":"locality"
},
  "geometry": {"coordinates":[8.29778,36.53639],"type":"Point"}
}