{
  "type": "Feature",
  "properties": {
    "gn:admin1_code":"00",
    "gn:asciiname":"Bou Saadia",
    "gn:country_code":"TN",
    "gn:dem":549,
    "gn:feature_class":"P",
    "gn:feature_code":"PPL",
    "gn:name":"Bou Saadia",
    "gn:population":0,
    "gn:timezone":"Africa/Tunis",
    "iso:country":"TN",
    "name:und_x_variant":[
        "B\u016b Sa\u2018d\u012byah"
    ],
    "wof:name":"Bou Saadia",
    "wof:placetype":"locality"
},
  "geometry": {"coordinates":[9.63939,36.04985],"type":"Point"}
}