{
  "type": "Feature",
  "properties": {
    "gn:admin1_code":"34",
    "gn:asciiname":"Krachoua",
    "gn:country_code":"TN",
    "gn:dem":407,
    "gn:feature_class":"P",
    "gn:feature_code":"PPL",
    "gn:name":"Krachoua",
    "gn:population":0,
    "gn:timezone":"Africa/Tunis",
    "iso:country":"TN",
    "name:und_x_variant":[
        "Ksar Krachoua",
        "Al Kar\u0101shiwah"
    ],
    "wof:name":"Krachoua",
    "wof:placetype":"locality"
},
  "geometry": {"coordinates":[10.56667,32.81667],"type":"Point"}
}