{
  "type": "Feature",
  "properties": {
    "gn:admin1_code":"00",
    "gn:asciiname":"Beni Aichoun",
    "gn:country_code":"TN",
    "gn:dem":11,
    "gn:feature_class":"P",
    "gn:feature_code":"PPL",
    "gn:name":"Beni A\u00efchoun",
    "gn:population":0,
    "gn:timezone":"Africa/Tunis",
    "iso:country":"TN",
    "name:und_x_variant":[
        "Ban\u012b \u2018Aysh\u016bn",
        "Beni A\u00efchoum",
        "Ben Aichoun",
        "Beni-Aychoun",
        "Beni A\u00efchoun"
    ],
    "wof:name":"Beni Aichoun",
    "wof:placetype":"locality"
},
  "geometry": {"coordinates":[10.84157,36.57587],"type":"Point"}
}