{
  "type": "Feature",
  "properties": {
    "gn:admin1_code":"14",
    "gn:asciiname":"El Haraig",
    "gn:country_code":"TN",
    "gn:dem":910,
    "gn:feature_class":"P",
    "gn:feature_code":"PPL",
    "gn:name":"El Hara\u00efg",
    "gn:population":0,
    "gn:timezone":"Africa/Tunis",
    "iso:country":"TN",
    "name:und_x_variant":[
        "Al \u1e28ar\u0101\u2019iq",
        "El Hara\u00efg"
    ],
    "wof:name":"El Haraig",
    "wof:placetype":"locality"
},
  "geometry": {"coordinates":[9.20111,35.79315],"type":"Point"}
}