{
  "type": "Feature",
  "properties": {
    "gn:asciiname":"Monastir-Skanes",
    "gn:country_code":"TN",
    "gn:dem":12,
    "gn:elevation":"2.0",
    "gn:feature_class":"P",
    "gn:feature_code":"PPL",
    "gn:name":"Monastir-Skanes",
    "gn:population":0,
    "gn:timezone":"Africa/Tunis",
    "iso:country":"TN",
    "wof:name":"Monastir-Skanes",
    "wof:placetype":"locality"
},
  "geometry": {"coordinates":[10.75,35.66667],"type":"Point"}
}