{
  "type": "Feature",
  "properties": {
    "gn:admin1_code":"03",
    "gn:asciiname":"Ouled Bel Firane",
    "gn:country_code":"TN",
    "gn:dem":222,
    "gn:feature_class":"P",
    "gn:feature_code":"PPL",
    "gn:name":"Ouled Bel Firane",
    "gn:population":0,
    "gn:timezone":"Africa/Tunis",
    "iso:country":"TN",
    "wof:name":"Ouled Bel Firane",
    "wof:placetype":"locality"
},
  "geometry": {"coordinates":[9.94667,35.99556],"type":"Point"}
}