{
  "type": "Feature",
  "properties": {
    "gn:gn_country":"TN",
    "gn:gn_fcode":"PPL",
    "gn:gn_pop":5009,
    "gn:population":5009,
    "iso:country":"TN",
    "name:ara_x_preferred":[
        "\u0633\u062c\u0646\u0627\u0646"
    ],
    "name:cat_x_preferred":[
        "Sejnane"
    ],
    "name:deu_x_preferred":[
        "Sejenane"
    ],
    "name:eng_x_preferred":[
        "Sejenane"
    ],
    "name:fra_x_preferred":[
        "Sejnane"
    ],
    "name:ita_x_preferred":[
        "Sejnane"
    ],
    "name:kab_x_preferred":[
        "Sejjnan"
    ],
    "name:nld_x_preferred":[
        "Sejenane"
    ],
    "name:ron_x_preferred":[
        "Sedjenane"
    ],
    "name:ukr_x_preferred":[
        "\u0421\u0435\u0436\u0435\u043d\u0430\u043d"
    ],
    "name:unk_x_variant":[
        "Sedjenane"
    ],
    "qs_pg:aaroncc":"TN",
    "qs_pg:gn_country":"TN",
    "qs_pg:gn_fcode":"PPL",
    "qs_pg:gn_pop":5009,
    "qs_pg:name":"Sejenane",
    "qs_pg:photos_9r":0,
    "qs_pg:photos_sr":0,
    "qs_pg:pop_sr":5,
    "qs_pg:qs_pg_placetype":"locality",
    "wof:name":"Sejenane",
    "wof:placetype":"locality",
    "wof:population":5009
},
  "geometry": {"coordinates":[9.23806,37.05722],"type":"Point"}
}