{
  "type": "Feature",
  "properties": {
    "gn:admin1_code":"19",
    "gn:asciiname":"Dar Khalifa Ben Hassene",
    "gn:country_code":"TN",
    "gn:dem":199,
    "gn:feature_class":"P",
    "gn:feature_code":"PPL",
    "gn:name":"Dar Khalifa Ben Hassene",
    "gn:population":0,
    "gn:timezone":"Africa/Tunis",
    "iso:country":"TN",
    "wof:name":"Dar Khalifa Ben Hassene",
    "wof:placetype":"locality"
},
  "geometry": {"coordinates":[10.89917,36.88722],"type":"Point"}
}