{
  "type": "Feature",
  "properties": {
    "gn:admin1_code":"29",
    "gn:asciiname":"Zarat",
    "gn:country_code":"TN",
    "gn:dem":30,
    "gn:feature_class":"P",
    "gn:feature_code":"PPL",
    "gn:name":"Zarat",
    "gn:population":0,
    "gn:timezone":"Africa/Tunis",
    "iso:country":"TN",
    "name:ara_x_preferred":[
        "\u0627\u0644\u0632\u0627\u0631\u0627\u062a"
    ],
    "name:ceb_x_preferred":[
        "Az Z\u0101r\u0101t"
    ],
    "name:deu_x_preferred":[
        "Zarat"
    ],
    "name:fra_x_preferred":[
        "Zarat"
    ],
    "name:ukr_x_preferred":[
        "\u0417\u0430\u0440\u0430\u0442"
    ],
    "name:und_x_variant":[
        "Zarath"
    ],
    "wof:lang_x_official":[
        "ara",
        "fra"
    ],
    "wof:lang_x_spoken":[
        "ara",
        "fra"
    ],
    "wof:name":"Zarat",
    "wof:placetype":"locality"
},
  "geometry": {"coordinates":[10.34896,33.66655],"type":"Point"}
}