{
  "type": "Feature",
  "properties": {
    "gn:admin1_code":"15",
    "gn:asciiname":"Salakta",
    "gn:cc2":"TN",
    "gn:country_code":"TN",
    "gn:dem":8,
    "gn:feature_class":"P",
    "gn:feature_code":"PPL",
    "gn:name":"Salakta",
    "gn:population":3477,
    "gn:timezone":"Africa/Tunis",
    "iso:country":"TN",
    "name:ara_x_preferred":[
        "\u0633\u0644\u0642\u0637\u0629"
    ],
    "name:und_x_variant":[
        "Salaq\u0163ah",
        "Salakta"
    ],
    "wof:name":"Salakta",
    "wof:placetype":"locality",
    "wof:population":3477
},
  "geometry": {"coordinates":[11.04361,35.39444],"type":"Point"}
}