{
  "type": "Feature",
  "properties": {
    "iso:country":"TN",
    "name:ara_x_preferred":[
        "\u0628\u0627\u0628 \u0627\u0644\u062e\u0636\u0631\u0627\u0621"
    ],
    "name:eng_x_preferred":[
        "Bab el Khadra"
    ],
    "name:fra_x_preferred":[
        "Bab El Khadra"
    ],
    "name:nld_x_preferred":[
        "Bab el Khadra"
    ],
    "qs:gn_country":"TN",
    "qs:gn_fcode":"PPL",
    "qs:gn_pop":0,
    "qs:name":"Bab El Khadra",
    "qs:name_adm0":"Tunisia",
    "qs:name_adm1":"Tunis",
    "qs:photos":46,
    "qs:photos_1k":9,
    "qs:photos_9k":1,
    "qs:photos_9r":2,
    "qs:photos_all":46,
    "qs:photos_sr":2,
    "qs:placetype":"Suburb",
    "qs:pop_sr":"0",
    "qs:woe_adm0":23424967,
    "wd:wordcount":61,
    "wof:name":"Bab El Khadra",
    "wof:placetype":"neighbourhood"
},
  "geometry": {"coordinates":[10.17611,36.80972],"type":"Point"}
}