{
  "type": "Feature",
  "properties": {
    "gn:admin1_code":"31",
    "gn:asciiname":"Guetaia",
    "gn:country_code":"TN",
    "gn:dem":30,
    "gn:feature_class":"P",
    "gn:feature_code":"PPL",
    "gn:name":"Gueta\u00efa",
    "gn:population":0,
    "gn:timezone":"Africa/Tunis",
    "iso:country":"TN",
    "name:und_x_variant":[
        "Qa\u0163\u0163\u0101yah",
        "Guetta\u00efa",
        "Guettaya",
        "Gueta\u00efa"
    ],
    "wof:name":"Guetaia",
    "wof:placetype":"locality"
},
  "geometry": {"coordinates":[8.87878,33.6788],"type":"Point"}
}