{
  "type": "Feature",
  "properties": {
    "gn:admin1_code":"00",
    "gn:asciiname":"Douar Ouled Bou Zaria",
    "gn:country_code":"TN",
    "gn:dem":471,
    "gn:feature_class":"P",
    "gn:feature_code":"PPL",
    "gn:name":"Douar Ouled Bou Zaria",
    "gn:population":0,
    "gn:timezone":"Africa/Tunis",
    "iso:country":"TN",
    "wof:name":"Douar Ouled Bou Zaria",
    "wof:placetype":"locality"
},
  "geometry": {"coordinates":[8.40361,36.54833],"type":"Point"}
}