{
  "type": "Feature",
  "properties": {
    "gn:admin1_code":"00",
    "gn:asciiname":"Douar Amor Cherina",
    "gn:country_code":"TN",
    "gn:dem":124,
    "gn:feature_class":"P",
    "gn:feature_code":"PPL",
    "gn:name":"Douar Amor Cherina",
    "gn:population":0,
    "gn:timezone":"Africa/Tunis",
    "iso:country":"TN",
    "name:und_x_variant":[
        "Dar Amor Cherina",
        "Douar Amor Cherina",
        "Daww\u0101r \u2018Umar Cherina"
    ],
    "wof:lang_x_official":[
        "ara",
        "fra"
    ],
    "wof:lang_x_spoken":[
        "ara",
        "fra"
    ],
    "wof:name":"Douar Amor Cherina",
    "wof:placetype":"locality"
},
  "geometry": {"coordinates":[9.66667,37.23333],"type":"Point"}
}