{
  "type": "Feature",
  "properties": {
    "gn:admin1_code":"28",
    "gn:asciiname":"Chebabia",
    "gn:country_code":"TN",
    "gn:dem":17,
    "gn:feature_class":"P",
    "gn:feature_code":"PPL",
    "gn:name":"Chebabia",
    "gn:population":0,
    "gn:timezone":"Africa/Tunis",
    "iso:country":"TN",
    "name:und_x_variant":[
        "Ash Shab\u0101b\u012byah"
    ],
    "wof:name":"Chebabia",
    "wof:placetype":"locality"
},
  "geometry": {"coordinates":[10.98333,33.76667],"type":"Point"}
}