{
  "type": "Feature",
  "properties": {
    "gn:admin1_code":"36",
    "gn:asciiname":"Graba",
    "gn:country_code":"TN",
    "gn:dem":95,
    "gn:feature_class":"P",
    "gn:feature_code":"PPL",
    "gn:name":"Graba",
    "gn:population":0,
    "gn:timezone":"Africa/Tunis",
    "iso:country":"TN",
    "wof:name":"Graba",
    "wof:placetype":"locality"
},
  "geometry": {"coordinates":[10.00944,36.81833],"type":"Point"}
}