{
  "type": "Feature",
  "properties": {
    "gn:admin1_code":"32",
    "gn:asciiname":"Dar el Haj Taieb",
    "gn:cc2":"TN",
    "gn:country_code":"TN",
    "gn:dem":24,
    "gn:feature_class":"P",
    "gn:feature_code":"PPL",
    "gn:name":"Dar el Haj Ta\u00efeb",
    "gn:population":0,
    "gn:timezone":"Africa/Tunis",
    "iso:country":"TN",
    "name:und_x_variant":[
        "Dar el Hadj Ta\u00efeb",
        "Dar el Haj Ta\u00efeb"
    ],
    "wof:lang_x_official":[
        "ara",
        "fra"
    ],
    "wof:lang_x_spoken":[
        "ara",
        "fra"
    ],
    "wof:name":"Dar el Haj Taieb",
    "wof:placetype":"locality"
},
  "geometry": {"coordinates":[10.74389,34.78444],"type":"Point"}
}