{
  "type": "Feature",
  "properties": {
    "iso:country":"TN",
    "name:ara_x_preferred":[
        "\u0627\u0644\u0645\u0633\u062f\u0648\u0631"
    ],
    "name:azb_x_preferred":[
        "\u0627\u0644\u0645\u0633\u062f\u0648\u0631"
    ],
    "name:ceb_x_preferred":[
        "Al Ma\u015fd\u016br"
    ],
    "name:eng_x_preferred":[
        "El Masdour"
    ],
    "name:fas_x_preferred":[
        "\u0627\u0644\u0645\u0633\u062f\u0648\u0631"
    ],
    "name:fra_x_preferred":[
        "El Masdour"
    ],
    "name:nld_x_preferred":[
        "El Masdour"
    ],
    "name:ukr_x_preferred":[
        "\u0415\u043b\u044c-\u041c\u0430\u0441\u0434\u0443\u0440"
    ],
    "name:und_x_variant":[
        "Mesdour"
    ],
    "qs:gn_country":"TN",
    "qs:gn_fcode":"PPL",
    "qs:gn_pop":3372,
    "qs:name":"Al Masdur",
    "qs:name_adm0":"Tunisia",
    "qs:name_adm1":"Al Munastir",
    "qs:photos":0,
    "qs:photos_1k":0,
    "qs:photos_9k":1,
    "qs:photos_9r":1,
    "qs:photos_all":2,
    "qs:photos_sr":0,
    "qs:placetype":"Town",
    "qs:pop_sr":"4",
    "qs:woe_adm0":23424967,
    "wd:wordcount":36,
    "wof:name":"Al Masdur",
    "wof:placetype":"locality",
    "wof:population":3372
},
  "geometry": {"coordinates":[10.72746,35.68206],"type":"Point"}
}