{
  "type": "Feature",
  "properties": {
    "gn:admin1_code":"29",
    "gn:asciiname":"Chabet Smala",
    "gn:country_code":"TN",
    "gn:dem":472,
    "gn:feature_class":"P",
    "gn:feature_code":"PPL",
    "gn:name":"Chabet Smala",
    "gn:population":0,
    "gn:timezone":"Africa/Tunis",
    "iso:country":"TN",
    "name:und_x_variant":[
        "Shu\u2018bat Zam\u0101lah"
    ],
    "wof:name":"Chabet Smala",
    "wof:placetype":"locality"
},
  "geometry": {"coordinates":[9.99957,33.50936],"type":"Point"}
}