{
  "type": "Feature",
  "properties": {
    "gn:admin1_code":"03",
    "gn:asciiname":"Dar Haj Ahmed Ben Ameur",
    "gn:country_code":"TN",
    "gn:dem":113,
    "gn:feature_class":"P",
    "gn:feature_code":"PPL",
    "gn:name":"Dar Haj Ahmed Ben Ameur",
    "gn:population":0,
    "gn:timezone":"Africa/Tunis",
    "iso:country":"TN",
    "name:und_x_variant":[
        "Dar Hadj Ahmed Ben Ameur",
        "Dar Haj Ahmed Ben Ameur"
    ],
    "wof:name":"Dar Haj Ahmed Ben Ameur",
    "wof:placetype":"locality"
},
  "geometry": {"coordinates":[9.96665,35.66564],"type":"Point"}
}