{
  "type": "Feature",
  "properties": {
    "gn:country":"TN",
    "gn:fcode":"PPL",
    "gn:population":60192,
    "iso:country":"TN",
    "name:ceb_x_preferred":[
        "Douane"
    ],
    "qs_pg:aaroncc":"TN",
    "qs_pg:gn_country":"TN",
    "qs_pg:gn_fcode":"PPL",
    "qs_pg:gn_pop":60192,
    "qs_pg:name":"Douane",
    "qs_pg:photos_9r":0,
    "qs_pg:photos_sr":0,
    "qs_pg:pop_sr":8,
    "qs_pg:qs_pg_placetype":"locality",
    "wof:name":"Douane",
    "wof:placetype":"locality",
    "wof:population":60192
},
  "geometry": {"coordinates":[10.7557,36.44766],"type":"Point"}
}