{
  "type": "Feature",
  "properties": {
    "gn:admin1_code":"15",
    "gn:asciiname":"Dar Brahim Ben Kahia",
    "gn:country_code":"TN",
    "gn:dem":87,
    "gn:feature_class":"P",
    "gn:feature_code":"PPL",
    "gn:name":"Dar Brahim Ben Kahia",
    "gn:population":0,
    "gn:timezone":"Africa/Tunis",
    "iso:country":"TN",
    "wof:name":"Dar Brahim Ben Kahia",
    "wof:placetype":"locality"
},
  "geometry": {"coordinates":[10.22111,35.38111],"type":"Point"}
}