{
  "type": "Feature",
  "properties": {
    "iso:country":"TN",
    "name:ara_x_preferred":[
        "\u0628\u0626\u0631 \u0627\u0644\u062d\u0641\u064a"
    ],
    "name:cat_x_preferred":[
        "Bir El Hfay"
    ],
    "name:ceb_x_preferred":[
        "Bi'r al \u1e28ufayy"
    ],
    "name:cym_x_preferred":[
        "Bir El Hafey"
    ],
    "name:eng_x_preferred":[
        "Bir El Hafey"
    ],
    "name:fra_x_preferred":[
        "Bir El Hafey"
    ],
    "name:ita_x_preferred":[
        "Bir El Hafey"
    ],
    "name:nld_x_preferred":[
        "Bir El Hafey"
    ],
    "name:ukr_x_preferred":[
        "\u0411\u0435\u0435\u0440-\u0435\u043b\u044c-\u0425\u0430\u0444\u0435\u0439"
    ],
    "name:und_x_variant":[
        "Bir el Afey"
    ],
    "qs:gn_country":"TN",
    "qs:gn_fcode":"PPL",
    "qs:gn_pop":5016,
    "qs:name":"Bi'r al Hufayy",
    "qs:name_adm0":"Tunisia",
    "qs:name_adm1":"Sidi Bu Zayd",
    "qs:photos":0,
    "qs:photos_1k":0,
    "qs:photos_9k":0,
    "qs:photos_9r":0,
    "qs:photos_all":0,
    "qs:photos_sr":0,
    "qs:placetype":"Town",
    "qs:pop_sr":"5",
    "qs:woe_adm0":23424967,
    "wd:wordcount":188,
    "wof:lang_x_official":[
        "ara",
        "fra"
    ],
    "wof:lang_x_spoken":[
        "ara",
        "fra"
    ],
    "wof:name":"Bi'r al Hufayy",
    "wof:placetype":"locality",
    "wof:population":5016
},
  "geometry": {"coordinates":[9.19321,34.93212],"type":"Point"}
}