{
  "type": "Feature",
  "properties": {
    "gn:admin1_code":"36",
    "gn:asciiname":"Zahrouni",
    "gn:country_code":"TN",
    "gn:dem":17,
    "gn:feature_class":"P",
    "gn:feature_code":"PPL",
    "gn:name":"Zahrouni",
    "gn:population":0,
    "gn:timezone":"Africa/Tunis",
    "iso:country":"TN",
    "name:und_x_variant":[
        "Az Zahr\u016bn\u012b",
        "Zahrouni"
    ],
    "wof:lang_x_official":[
        "ara",
        "fra"
    ],
    "wof:lang_x_spoken":[
        "ara",
        "fra"
    ],
    "wof:name":"Zahrouni",
    "wof:placetype":"locality"
},
  "geometry": {"coordinates":[10.11111,36.78944],"type":"Point"}
}