{
  "type": "Feature",
  "properties": {
    "gn:admin1_code":"34",
    "gn:asciiname":"Ksar Oum er Roumanat",
    "gn:country_code":"TN",
    "gn:dem":504,
    "gn:feature_class":"P",
    "gn:feature_code":"PPL",
    "gn:name":"Ksar Oum er Roumanat",
    "gn:population":0,
    "gn:timezone":"Africa/Tunis",
    "iso:country":"TN",
    "name:und_x_variant":[
        "Qa\u015fr Umm ar Rumm\u0101n\u0101t"
    ],
    "wof:lang_x_official":[
        "ara",
        "fra"
    ],
    "wof:lang_x_spoken":[
        "ara",
        "fra"
    ],
    "wof:name":"Ksar Oum er Roumanat",
    "wof:placetype":"locality"
},
  "geometry": {"coordinates":[10.19127,32.78382],"type":"Point"}
}