{
  "type": "Feature",
  "properties": {
    "gn:admin1_code":"32",
    "gn:asciiname":"Hencha",
    "gn:country_code":"TN",
    "gn:dem":53,
    "gn:feature_class":"P",
    "gn:feature_code":"PPL",
    "gn:name":"Hencha",
    "gn:population":0,
    "gn:timezone":"Africa/Tunis",
    "iso:country":"TN",
    "name:und_x_variant":[
        "La Hencha",
        "Al \u1e28anashah"
    ],
    "wof:name":"Hencha",
    "wof:placetype":"locality"
},
  "geometry": {"coordinates":[10.74219,35.12226],"type":"Point"}
}