{
  "type": "Feature",
  "properties": {
    "gn:admin1_code":"19",
    "gn:asciiname":"Grombalia",
    "gn:country_code":"TN",
    "gn:dem":50,
    "gn:feature_class":"P",
    "gn:feature_code":"PPL",
    "gn:name":"Grombalia",
    "gn:population":0,
    "gn:timezone":"Africa/Tunis",
    "iso:country":"TN",
    "name:ara_x_preferred":[
        "\u0642\u0631\u0645\u0628\u0627\u0644\u064a\u0629"
    ],
    "name:cat_x_preferred":[
        "Grombalia"
    ],
    "name:ceb_x_preferred":[
        "Grombalia"
    ],
    "name:cym_x_preferred":[
        "Grombalia"
    ],
    "name:deu_x_preferred":[
        "Grombalia"
    ],
    "name:fra_x_preferred":[
        "Grombalia"
    ],
    "name:heb_x_preferred":[
        "\u05d2\u05e8\u05d5\u05de\u05d1\u05dc\u05d9\u05d4"
    ],
    "name:ita_x_preferred":[
        "Grombalia"
    ],
    "name:kor_x_preferred":[
        "\uadf8\ub86c\ubc1c\ub9ac\uc544"
    ],
    "name:ukr_x_preferred":[
        "\u041a\u0440\u043e\u043c\u0431\u0430\u043b\u044c\u044f"
    ],
    "name:und_x_variant":[
        "Quranb\u0101liyah",
        "Grombalic",
        "Quaranbaliyah",
        "Qurunb\u0101liyah",
        "Grombalia"
    ],
    "wof:name":"Grombalia",
    "wof:placetype":"locality"
},
  "geometry": {"coordinates":[10.50032,36.59894],"type":"Point"}
}