{
  "type": "Feature",
  "properties": {
    "gn:admin1_code":"00",
    "gn:asciiname":"Sidi Daoud",
    "gn:cc2":"TN",
    "gn:country_code":"TN",
    "gn:dem":0,
    "gn:feature_class":"P",
    "gn:feature_code":"PPL",
    "gn:name":"Sidi Daoud",
    "gn:population":0,
    "gn:timezone":"Africa/Tunis",
    "iso:country":"TN",
    "name:ara_x_preferred":[
        "\u0633\u064a\u062f\u064a \u062f\u0627\u0648\u062f"
    ],
    "name:eng_x_preferred":[
        "Sidi Daoud"
    ],
    "name:por_x_preferred":[
        "Sidi Daoud"
    ],
    "name:und_x_variant":[
        "Sidi Daud",
        "S\u012bd\u012b D\u0101\u2019\u016bd",
        "Sidi Daoud"
    ],
    "wof:name":"Sidi Daoud",
    "wof:placetype":"locality"
},
  "geometry": {"coordinates":[10.895,37.00167],"type":"Point"}
}