{
  "type": "Feature",
  "properties": {
    "gn:admin1_code":"00",
    "gn:asciiname":"Sidi Daoud",
    "gn:cc2":"TN",
    "gn:country_code":"TN",
    "gn:dem":0,
    "gn:feature_class":"P",
    "gn:feature_code":"PPL",
    "gn:name":"Sidi Daoud",
    "gn:population":0,
    "gn:timezone":"Africa/Tunis",
    "iso:country":"TN",
    "name:ara_x_preferred":[
        "\u0633\u064a\u062f\u064a \u062f\u0627\u0648\u062f"
    ],
    "name:ceb_x_preferred":[
        "Sidi Daoud"
    ],
    "name:eng_x_preferred":[
        "Sidi Daoud"
    ],
    "name:fra_x_preferred":[
        "Sidi Daoud"
    ],
    "name:ita_x_preferred":[
        "Sidi Daoud"
    ],
    "name:kab_x_preferred":[
        "Sidi Dawed"
    ],
    "name:msa_x_preferred":[
        "Sidi Daoud"
    ],
    "name:por_x_preferred":[
        "Sidi Daoud"
    ],
    "name:ron_x_preferred":[
        "Sidi Daoud"
    ],
    "name:rus_x_preferred":[
        "\u0421\u0438\u0434\u0438-\u0414\u0430\u0443\u0434"
    ],
    "name:spa_x_preferred":[
        "Sidi Daoud"
    ],
    "name:swe_x_preferred":[
        "Sidi Daoud"
    ],
    "name:und_x_variant":[
        "Sidi Daud",
        "S\u012bd\u012b D\u0101\u2019\u016bd"
    ],
    "name:vie_x_preferred":[
        "Sidi Daoud"
    ],
    "wof:lang_x_official":[
        "ara",
        "fra"
    ],
    "wof:lang_x_spoken":[
        "ara",
        "fra"
    ],
    "wof:name":"Sidi Daoud",
    "wof:placetype":"locality"
},
  "geometry": {"coordinates":[10.895,37.00167],"type":"Point"}
}